Workbook
Name \a: #REF!
Name \b: #REF!
Name \c: #REF!
Name \d: #REF!
Name \h: #REF!
Name \i: #REF!
Name \l: #REF!
Name \p: #N/A
Name \r: #REF!
Name \s: #REF!
Name \t: #REF!
Name \u: #REF!
Name \v: #REF!
Name \y: #REF!
Name _136_070423_製品系統付け: #REF!
Name _GMT610: [0]!_GMT610
Name _SUB1: #REF!
Name _SUM1: #REF!
Name _SUM2: #REF!
Name A: #REF!
Name aa: [0]!aa
Name AB: #REF!
Name Advertising_Promotions: #REF!
Name after: [0]!after
Name after2: [0]!after2
Name Agreed_Direct: #REF!
Name Agreed_Indirect: #REF!
Name Agreed_Labor: #REF!
Name Agreed_Material: #REF!
Name Agreed_MBFT: #REF!
Name Agreed_Profit: #REF!
Name Agreed_SGA: #REF!
Name Annual_Days: '[7]Machine Data'!$I$6
Name Annual_Uptime: '[7]Machine Data'!$C$18
Name Assembly_Operations: '[7]Machine Rate Data'!$B$8:$B$12
Name Assembly_Time: #REF!
Name B: #REF!
Name Bad_Debt_Expense: #REF!
Name Battery_Cable_Harness: '[7]Material Data'!$AH$9:$AH$18
Name BC: #REF!
Name Benefits: #REF!
Name bf: #REF!
Name BillOfMaterial: '[8]Bill of Mat'!$A$4:$I$61
Name Building: #REF!
Name Building_Maintenance: #REF!
Name Bus._Computer_Equip: #REF!
Name C.I.P.__1: #REF!
Name C.I.P.__2: #REF!
Name C.I.P.__3: #REF!
Name C.I.P.__4: #REF!
Name C.I.P.__5: #REF!
Name C.I.P.__6: #REF!
Name CAPITAL: #REF!
Name CD: #REF!
Name Chart: '[9]Machine Balance'!$C$57
Name CIP_Ideas: #REF!
Name ClearData: [0]!ClearData
Name CLIP: '[7]2005 DGSS Component Prices'!$D$2:$D$1320
Name CNSLD: #REF!
Name CO: #REF!

Sheet 11予算諸元表
A1: 2011年度見積諸元表
A2: １．直接費 一覧
B3: 部門 | D3: 部門コード | E3: 直間比 | F3: ＭＨ単価 | G3: ＭＴ単価 | H3: MPC
B4: AE実装 | D4: UBAE | E4: 1.15 | F4: 2679.4 | G4: 6920.6 | H4: AE作業組
B5: AE後工程 | D5: UBAF | E5: 1.15 | F5: 2679.4 | G5: 1369.5 | H5: AE作業組
B6: AE MT無し | D6: UBM1 | E6: 1.15 | F6: 2679.4 | G6: 0 | H6: AE作業組 | I6: ←設備の無い工程
B7: AH多工程 | D7: UBAH | E7: 1.28 | F7: 2330.1 | G7: 2521.3 | H7: AH作業組
B8: AH単発 | D8: UBAI | E8: 1.28 | F8: 2330.1 | G8: 474.8 | H8: AH作業組
B9: AH MT無し | D9: UBM6 | E9: 1.28 | F9: 2330.1 | G9: 0 | H9: AH作業組 | I9: ←設備の無い工程
B10: AM組立 | D10: UBAM | E10: 1.18 | F10: 2357.1 | G10: 1408.7 | H10: AM作業組
B11: AM MT無し | D11: UBM2 | E11: 1.18 | F11: 2357.1 | G11: 0 | H11: AM作業組 | I11: ←設備の無い工程
B12: AS多工程 | D12: UBAS | E12: 1.37 | F12: 2022.6 | G12: 957.4 | H12: AS作業組
B13: AS MT無し | D13: UBM3 | E13: 1.37 | F13: 2022.6 | G13: 0 | H13: AS作業組 | I13: ←設備の無い工程
B14: JB成形 | D14: UBJB | E14: 1.21 | F14: 2879.5 | G14: 1779.4 | H14: JB作業組
B15: JB MT無し | D15: UBM0 | E15: 1.21 | F15: 2879.5 | G15: 0 | H15: JB作業組 | I15: ←設備の無い工程
B16: JC旧成形 | D16: UBJC | E16: 1.19 | F16: 2390.8 | G16: 1155.6 | H16: JC作業組 | I16: ※見積用 MT単価 (11年標準 1327.2）
B17: JC新成形 | D17: UBJD | E17: 1.19 | F17: 2390.8 | G17: 1264.5 | H17: JC作業組
B18: JP400トンプレス | D18: UBJP | E18: 1.13 | F18: 2608.9 | G18: 5391.7 | H18: JP作業組
B19: JP高速プレス | D19: UBJQ | E19: 1.13 | F19: 2608.9 | G19: 3729.4 | H19: JP作業組 | I19: ※見積用 MT単価 (11年標準 4227.5）
B20: JP積層プレス | D20: UBJR | E20: 1.13 | F20: 2608.9 | G20: 1372.1 | H20: JP作業組
B21: JP MT無し | D21: UBM8 | E21: 1.13 | F21: 2608.9 | G21: 0 | H21: JP作業組 | I21: ←設備の無い工程
B22: JSブロック | D22: UBJS | E22: 1.14 | F22: 1993 | G22: 1537.6 | H22: JS作業組
B23: JSコネクタ二次加工 | D23: UBJU | E23: 1.14 | F23: 1993 | G23: 533.1 | H23: JS作業組
B24: JS MT無し | D24: UBM4 | E24: 1.14 | F24: 1993 | G24: 0 | H24: JS作業組 | I24: ←設備の無い工程
B25: RBラミネート | D25: UBRF | E25: 1.12 | F25: 2761.4 | G25: 1031.7862 | H25: RB作業組 | I25: ※見積用 MT単価 (11年標準 1,311.4)
B26: RB束取 | D26: UBRG | E26: 1.12 | F26: 2761.4 | G26: 2305.7 | H26: RB作業組
B27: RB圧延 | D27: UBRP | E27: 1.12 | F27: 2761.4 | G27: 586.00337 | H27: RB作業組 | I27: ※見積用 MT単価 (11年標準 645.4)
B28: RB MT無し | D28: UBM5 | E28: 1.12 | F28: 2761.4 | G28: 0 | H28: RB作業組 | I28: ←設備の無い工程
B29: RC | D29: UBRC | E29: 1.23 | F29: 2323.4 | G29: 2088.3 | H29: RC作業組
B30: 杉本電装（内作） | D30: UBSD | E30: 1 | F30: 0 | G30: 847.7 | H30: 杉本電装（社内付）
B31: 保田産業（内作） | D31: UBYS | E31: 1 | F31: 0 | G31: 1111.1 | H31: 保田作業（社内付） | I31: ←梱包・選別・コネクタ組立など
B32: 再検査 | D32: UBRI | E32: 1 | F32: 0 | G32: 2319.1 | H32: 古河ライフ | I32: ←SRC再検査工程
B33: ★「MT無し」の工程は、設備などが存在せず、動力料や修繕費の掛からない工程に使用する。
B34: 例) 梱包工程、目視選別工程など
A36: ２．販売直接費 | E36: ※対直原比率
B37: 販売直接費は、下記①～②の合計もしくは個別に見積もった販直費を計上する。
B39: ①工場販直費(国内)
C40: 三重工場から出荷する際の輸送・梱包資材・出荷作業の費用は、下記の比率を用いる。
C41: 輸送費・梱包資材費を別途計上している場合は、2.・3.の比率を用いること.。
E43: 輸送費 | F43: 梱包資材費 | G43: 出荷作業 | H43: 工場販直
B44: 1. 全て直原比率で算出 | E44: 0.0092088228 | F44: 0.010264874 | G44: 0.0036972816 | H44: =SUM(E44:G44) -> 0.023170979
B45: 2. 輸送費を別途計上 | E45: 0 | F45: 0.010264874 | G45: 0.0036972816 | H45: =SUM(E45:G45) -> 0.013962156
B46: 3. 輸送費・梱包資材費を別途計上 | E46: 0 | F46: 0 | G46: 0.0036972816 | H46: =SUM(E46:G46) -> 0.0036972816
B48: ②営業販直費(国内)
C49: ※国内の営業販直費は、SCを経由しない場合は０とする。
C50: 国内 | E50: 営業販直
C51: SCを経由しない | E51: 0
C52: マツダ | E52: 0.0123133
C53: ダイハツ | E53: 0.0085972742
C54: ホンダ鈴鹿 | E54: 0.013556089 | F54: ※2008年値
C55: ホンダ狭山 | E55: 0.013725746 | F55: ※2008年値
C56: トヨタ | E56: 0.011559355
C57: スズキ・ヤマハ | E57: 0.010725969
C58: 富士重 | E58: 0.010725969 | F58: ※予算無し
C59: いすゞ | E59: 0.05030343
B65: ③海外向け販直費(工場販直費＋営業販直費)
C66: 海外拠点へ輸出する際の販直費は、個別に別紙の算出フォーマットを用いて輸送費を
C67: 計算し、別途計上すること。
C68: ※別紙「海外向け輸送費算出計算書_2010.xls」を参照すること。
A71: ３．工場間接費・一般管理費 | F71: ※対直原比率
B73: ①古河AS三重工場 間接費・管理費 直原比率一覧
D74: ブロック | E74: ＳＲＣ | F74: コネクタ | G74: 電子部品※1 | H74: スマコネ | I74: アンテナ※2 | J74: 平均
B75: 工場間接費 | D75: 0.089495565 | E75: 0.14516844 | F75: 0.13367012 | G75: 0.11282736 | H75: 0.1020688 | I75: 0.12230239 | J75: 0.12230239
B76: 一般管理費 | D76: 0.082573264 | E76: 0.10239413 | F76: 0.1397124 | G76: 0.096822429 | H76: 0.054826561 | J76: 0.096822429
B77: 電工本社費 | D77: 0.0010160453 | E77: 0.0010160453 | F77: 0.0010160453 | G77: 0.0010160453 | H77: 0.0010160453 | J77: 0.0010160453
D78: (工場間接費は専用設備の償却費を除く｡) | I78: ※2 工場平均値
G79: ※1 一般管理費は工場平均値
B81: ①-1.工場間接費 比率内訳
D82: ブロック | E82: ＳＲＣ | F82: コネクタ | G82: 電子部品 | H82: スマコネ | I82: アンテナ※2 | J82: 平均
B83: 人件費・その他 | D83: 0.071030171 | E83: 0.14229332 | F83: 0.10326428 | G83: 0.10769959 | H83: 0.085208159 | I83: 0.1040782 | J83: 0.1040782
C84: 生産技術 | D84: 0.023032829 | E84: 0.05468237 | F84: 0.034880665 | G84: 0.056294235 | H84: 0.028718615 | I84: 0.037118799 | J84: 0.037118799
C85: 生産管理 | D85: 0.010577624 | E85: 0.015056491 | F85: 0.015083543 | G85: 0.046663325 | H85: 0.013228255 | I85: 0.014556392 | J85: 0.014556392
C86: 品質保証 | D86: 0.016849816 | E86: 0.043802477 | F86: 0.019375296 | G86: 0.0015841465 | H86: 0.015343147 | I86: 0.026201505 | J86: 0.026201505
C87: その他 | D87: 0.020569902 | E87: 0.028751983 | F87: 0.033924773 | G87: 0.0031578872 | H87: 0.027918142 | I87: 0.026201505 | J87: 0.026201505
B88: 研究費 | D88: 0.0016044362 | E88: 0.0029168556 | F88: 0.0012825056 | G88: 0.0022080733 | H88: 0.0010789437 | I88: 0.0018571096 | J88: 0.0018571096
B89: 家賃 | D89: 0.028925251 | E89: 0.014135919 | F89: 0.049432031 | G89: 0.014103164 | H89: 0.027110827 | I89: 0.030186698 | J89: 0.030186698
B90: 償却費(共通設備) | D90: 0.00070411753 | E90: 0.00098419406 | F90: 0.0011612611 | G90: 0.00010809598 | H90: 0.00095565131 | I90: 0.0008966055 | J90: 0.0008966055
B91: ロイヤルティ収入 | D91: -0.012768411 | E91: -0.015161848 | F91: -0.021469951 | G91: -0.011291568 | H91: -0.012284779 | I91: -0.014683211 | J91: -0.014683211 | K91: ※海外支援収入
D92: =D83+D88+D89+D90+D91 -> 0.089495565 | E92: =E83+E88+E89+E90+E91 -> 0.14516844 | F92: =F83+F88+F89+F90+F91 -> 0.13367012 | G92: =G83+G88+G89+G90+G91 -> 0.11282736 | H92: =H83+H88+H89+H90+H91 -> 0.1020688 | I92: =I83+I88+I89+I90+I91 -> 0.1223354 | J92: =J83+J88+J89+J90+J91 -> 0.1223354
B94: ①-2.一般管理費 比率内訳
D95: ブロック | E95: ＳＲＣ | F95: コネクタ | G95: 電子部品 | H95: スマコネ | J95: 平均
B96: 設計部門 | D96: 0.051749164 | E96: 0.057920826 | F96: 0.089088817 | G96: 0.061425759 | H96: 0.033921167 | J96: 0.061425759
B97: 営業部門 | D97: 0.012705209 | E97: 0.017758954 | F97: 0.020953981 | G97: 0.01459358 | H97: 0.0092530879 | J97: 0.01459358
B98: 古河AS 管理本部 | D98: 0.024719863 | E98: 0.034552672 | F98: 0.040769069 | G98: 0.028393968 | H98: 0.018003251 | J98: 0.028393968
B99: ロイヤルティ収入 | D99: -0.0066009711 | E99: -0.0078383222 | F99: -0.011099465 | G99: -0.0075640785 | H99: -0.0063509449 | J99: -0.0075640785 | K99: ※海外支援収入
D100: =D96+D97+D98+D99 -> 0.082573264 | E100: =E96+E97+E98+E99 -> 0.10239413 | F100: =F96+F97+F98+F99 -> 0.1397124 | G100: =G96+G97+G98+G99 -> 0.096849229 | H100: =H96+H97+H98+H99 -> 0.054826561 | J100: =J96+J97+J98+J99 -> 0.096849229
B102: 商流 | F102: FAS本部 工間・一般管適用
C103: 日本⇒日本出荷 | F103: 客先へ出荷する製品に比率を適用する。
B106: Out-In | C106: (日本⇒)海外⇒日本出荷 | F106: 客先へ出荷する製品に比率を適用する。
F107: (日供部材には賦課しない。)
B109: Out-Out | C109: (日本⇒)海外⇒海外出荷 | F109: 日供部材に対して比率を適用する。
F110: ※1 支援費用は別途計上すること。
C112: ※注：「日本への逆輸入品」に使用する「日供部材」の輸出には賦課しない。
B114: ※1 Out-Out製品 支援費用 ： Out-Out製品に対する古河AS本部スタッフの間接費・管理費は、
B115: 海外拠点が古河電工に支払うロイヤルティ等に含まれる。(別途、古河電工から古河ASへ支払。)
B116: ロイヤルティが原価に含まれていない場合は、個別に支援費用を見積もるか、
B117: ①の内訳から生産技術・設計・営業部門など支援部門の比率(ロイヤルティ収入分を含む)で算出すること。
A129: ４．２０１１年度標準銅ベース | F129: 750 | G129: 円/KG
A132: ５．２０１１年度標準為替レート 一覧
C133: 米ドル | E133: USD | F133: 85 | G133: 円
...

Sheet 13予算諸元表
A1: 2013年度見積諸元表
A2: １．直接費 一覧
B3: 部門 | D3: 部門コード | E3: 直間比 | F3: ＭＨ単価 | G3: ＭＴ単価 | H3: MPC
B4: AE実装 | D4: UBAE | E4: 1.25 | F4: 2463.8 | G4: 7486.7 | H4: AE作業組
B5: AE後工程 | D5: UBAF | E5: 1.25 | F5: 2463.8 | G5: 3358.7 | H5: AE作業組
B6: AE MT無し | D6: UBM1 | E6: 1.25 | F6: 2463.8 | G6: 0 | H6: AE作業組 | I6: ←設備の無い工程
B7: AH多工程 | D7: UBAH | E7: 1.27 | F7: 2340 | G7: 4101.9 | H7: AH作業組
B8: AH単発 | D8: UBAI | E8: 1.27 | F8: 2340 | G8: 682.9 | H8: AH作業組
B9: AH MT無し | D9: UBM6 | E9: 1.27 | F9: 2340 | G9: 0 | H9: AH作業組 | I9: ←設備の無い工程
B10: AM組立 | D10: UBAM | E10: 1.15 | F10: 2185.1 | G10: 4058.8 | H10: AM作業組
B11: AM MT無し | D11: UBM2 | E11: 1.15 | F11: 2185.1 | G11: 0 | H11: AM作業組 | I11: ←設備の無い工程
B12: AS多工程 | D12: UBAS | E12: 1.72 | F12: 1907.3 | G12: 1168.9 | H12: AS作業組
B13: AS MT無し | D13: UBM3 | E13: 1.72 | F13: 1907.3 | G13: 0 | H13: AS作業組 | I13: ←設備の無い工程
B14: JB成形 | D14: UBJB | E14: 1.15 | F14: 2822.5 | G14: 1641.5 | H14: JB作業組
B15: JB MT無し | D15: UBM0 | E15: 1.15 | F15: 2822.5 | G15: 0 | H15: JB作業組 | I15: ←設備の無い工程
B16: JC旧成形 | D16: UBJC | E16: 1.14 | F16: 2338.6 | G16: 1300.6 | H16: JC作業組
B17: JC新成形 | D17: UBJD | E17: 1.14 | F17: 2338.6 | G17: 1178.5 | H17: JC作業組
B18: JC MT無し | D18: UBM7 | E18: 1.14 | F18: 2338.6 | G18: 0 | H18: JC作業組 | I18: ←設備の無い工程
B19: JP400トンプレス | D19: UBJP | E19: 1.13 | F19: 3027.4 | G19: 4118 | H19: JP作業組
B20: JP高速プレス | D20: UBJQ | E20: 1.13 | F20: 3027.4 | G20: 3965.2 | H20: JP作業組
B21: JSブロック | D21: UBJS | E21: 1.22 | F21: 2447.8 | G21: 1474 | H21: JS作業組
B22: JSコネクタ二次加工 | D22: UBJU | E22: 1.22 | F22: 2447.8 | G22: 512.5 | H22: JS作業組
B23: JS MT無し | D23: UBM4 | E23: 1.22 | F23: 2447.8 | G23: 0 | H23: JS作業組 | I23: ←設備の無い工程
B24: RBラミネート | D24: UBRF | E24: 1.09 | F24: 2424.1 | G24: 938.9 | H24: RB作業組
B25: RB束取 | D25: UBRG | E25: 1.09 | F25: 2424.1 | G25: 1690.5 | H25: RB作業組
B26: RB圧延 | D26: UBRP | E26: 1.09 | F26: 2424.1 | G26: 885 | H26: RB作業組
B27: RB MT無し | D27: UBM5 | E27: 1.09 | F27: 2424.1 | G27: 0 | H27: RB作業組 | I27: ←設備の無い工程
B28: RC | D28: UBRC | E28: 1.23 | F28: 2350.1 | G28: 3641.4 | H28: RC作業組
B29: 杉本電装（内作） | D29: UBSD | E29: 1 | F29: 0 | G29: 1498.4 | H29: 杉本電装（社内付）
B30: 保田産業（内作） | D30: UBYS | E30: 1 | F30: 0 | G30: 1718.1 | H30: 保田作業（社内付） | I30: ←梱包・選別・コネクタ組立など
B31: 桑名作業 | D31: UBRK | E31: 1 | H31: 桑名B/C | I31: ←BUSハーネス/SRC検査
B32: 再検査 | D32: UBRI | E32: 1 | F32: 0 | G32: 5888.6 | H32: 古河ライフ | I32: ←桑名へ移管
B33: ★「MT無し」の工程は、設備などが存在せず、動力料や修繕費の掛からない工程に使用する。
B34: 例) 梱包工程、目視選別工程など
A36: ２．販売直接費 | E36: ※対直原比率
B37: 販売直接費は、下記①～②の合計もしくは個別に見積もった販直費を計上する。
B39: ①工場販直費(国内)
C40: 三重工場から出荷する際の輸送・梱包資材・出荷作業の費用は、下記の比率を用いる。
C41: 輸送費・梱包資材費を別途計上している場合は、2.・3.の比率を用いること.。
E43: 輸送費 | F43: 梱包資材費 | G43: 出荷作業 | H43: 工場販直
B44: 1. 全て直原比率で算出 | E44: 0.0074518168 | F44: 0.0077117378 | G44: 0.00753827 | H44: =SUM(E44:G44) -> 0.022701824
B45: 2. 輸送費を別途計上 | E45: 0 | F45: 0.0077117378 | G45: 0.00753827 | H45: =SUM(E45:G45) -> 0.015250008
B46: 3. 輸送費・梱包資材費を別途計上 | E46: 0 | F46: 0 | G46: 0.00753827 | H46: =SUM(E46:G46) -> 0.00753827
B48: ②営業販直費(国内)
C49: ※国内の営業販直費は、SCを経由しない場合は０とする。
C50: 国内 | E50: 営業販直
C51: SCを経由しない | E51: 0
C52: マツダ | E52: 0.0069561999
C53: ダイハツ | E53: 0.0073304712
C54: ホンダ鈴鹿 | E54: 0.01452366
C55: ホンダ狭山
C56: トヨタ | E56: 0.0098186522
C57: スズキ・ヤマハ | E57: 0.016892515
C58: 富士重
C59: いすゞ | E59: 0.045350999
B64: ③海外向け販直費(工場販直費＋営業販直費)
C65: 海外拠点へ輸出する際の販直費は、個別に別紙の算出フォーマットを用いて輸送費を
C66: 計算し、別途計上すること。
C67: ※別紙「海外向け輸送費算出計算書_2010.xls」を参照すること。
A70: ３．工場間接費・一般管理費 | F70: ※対直原比率
B72: ①古河AS三重工場出荷品 間接費・管理費 直原比率一覧
D73: ブロック | E73: ＳＲＣ | F73: コネクタ | G73: 電子部品 | H73: スマコネ | I73: 平均
B74: 工場間接費 | D74: 0.042025596 | E74: 0.13685764 | F74: 0.13439753 | G74: 0.071034499 | H74: 0.040436295 | I74: 0.075530042
B75: 一般管理費 | D75: 0.063880174 | E75: 0.12427198 | F75: 0.10249603 | G75: 0.066861705 | H75: 0.06968486 | I75: 0.082315819
B76: 電工本社費
D77: (工場間接費は専用設備の償却費を除く｡)
B79: ①-1.工場間接費 比率内訳
D80: ブロック | E80: ＳＲＣ | F80: コネクタ | G80: 電子部品 | H80: スマコネ | I80: 平均
B81: 人件費・その他 | D81: 0.04897692 | E81: 0.11800226 | F81: 0.11562965 | G81: 0.064831058 | H81: 0.030457773 | I81: 0.07928917
C82: 生産技術 | D82: 0.023585103 | E82: 0.046505252 | F82: 0.052866037 | G82: 0.033286331 | H82: 0.0096315874 | I82: 0.036040532
C83: 生産管理 | D83: 0.0060429559 | E83: 0.0070638864 | F83: 0.01687199 | G83: 0.0069615997 | H83: 0.0058446331 | I83: 0.0082378358
C84: 品質保証 | D84: 0.0098350044 | E84: 0.049278718 | F84: 0.023845968 | G84: 0.010442743 | H84: 0.0046100258 | I84: 0.021109454
C85: その他 | D85: 0.0095138568 | E85: 0.015154401 | F85: 0.022045652 | G85: 0.014140384 | H85: 0.010371527 | I85: 0.013901348
B86: 研究費 | D86: 0.0012950487 | E86: 0.0029654703 | F86: 0.0029562236 | G86: 0.0016771781 | H86: 0.000868148 | I86: 0.0018798443
B87: 家賃 | D87: 0.017495749 | E87: 0.025285296 | F87: 0.048692957 | G87: 0.0097722686 | H87: 0.010842242 | I87: 0.021019277
B88: 償却費(共通設備) | D88: 0.00036032945 | E88: 0.00045162914 | F88: 0.00057815022 | G88: 0.0003771474 | H88: 0.00039307199 | I88: 0.00040907009
B89: ロイヤルティ収入 | D89: -0.0029824262 | E89: -0.0098470082 | F89: -0.013392206 | G89: -0.0056231526 | H89: -0.0021249397 | I89: -0.0057721727
B90: FAPV成形移管効果 | D90: -0.023120024 | E90: 0 | F90: -0.020067243 | G90: 0 | H90: 0 | I90: -0.021295121
D91: =D81+D86+D87+D88+D89+D90 -> 0.042025596 | E91: =E81+E86+E87+E88+E89+E90 -> 0.13685764 | F91: =F81+F86+F87+F88+F89+F90 -> 0.13439753 | G91: =G81+G86+G87+G88+G89+G90 -> 0.071034499 | H91: =H81+H86+H87+H88+H89+H90 -> 0.040436295 | I91: =I81+I86+I87+I88+I89+I90 -> 0.075530068
B93: ①-2.一般管理費 比率内訳
D94: ブロック | E94: ＳＲＣ | F94: コネクタ | G94: 電子部品 | H94: スマコネ | I94: 平均
B95: 営業部門 | D95: 0.013455053 | E95: 0.016864272 | F95: 0.021588692 | G95: 0.014083051 | H95: 0.014677691 | I95: 0.015274102
B96: 設計部門 | D96: 0.033878476 | E96: 0.088203597 | F96: 0.054358167 | G96: 0.035459714 | H96: 0.036956957 | I96: 0.048598349
B97: FAS本社 管理部門 | D97: 0.025689973 | E97: 0.032199257 | F97: 0.041219678 | G97: 0.026889022 | H97: 0.028024379 | I97: 0.029163117
B98: ロイヤルティ配賦 | D98: -0.0091433277 | E98: -0.012995144 | F98: -0.01467051 | G98: -0.0095700817 | H98: -0.0099741668 | I98: -0.010719749
D99: =SUM(D95:D98) -> 0.063880174 | E99: =SUM(E95:E98) -> 0.12427198 | F99: =SUM(F95:F98) -> 0.10249603 | G99: =SUM(G95:G98) -> 0.066861705 | H99: =SUM(H95:H98) -> 0.06968486 | I99: =SUM(I95:I98) -> 0.082315819
B101: ②OUT－OUT製品の海外拠点に対するスタッフ支援による間接費・管理費は、OUT-OUT工数の
B102: 付替えなどで請求するため、海外拠点のロイヤルティ支出として海外拠点の間接費・管理費に含む。
A105: ４．２０１３年度標準銅ベース | F105: 655 | G105: 円/KG
A107: ５．２０１３年度標準為替レート 一覧
C108: 米ドル | E108: USD | F108: 90 | G108: 円
C109: ユ－ロ | E109: EUR | F109: 105 | G109: 円
C110: ｽﾀ-ﾘﾝｸﾞﾎﾟﾝﾄﾞ | E110: GBP | F110: 131.74 | G110: 円
C111: 香港ﾄﾞﾙ | E111: HKD | F111: 10.6 | G111: 円
C112: ｼﾝｶﾞﾎﾟ-ﾙﾄﾞﾙ | E112: SGD | F112: 67.3 | G112: 円
C113: 中国元 | E113: CNY,RMB | F113: 13 | G113: 円
C114: ﾀｲﾊﾞ-ﾂ | E114: THB | F114: 2.68 | G114: 円
C115: ﾌｨﾘﾋﾟﾝﾍﾟｿ | E115: PHP | F115: 2.03 | G115: 円
C116: ｲﾝﾄﾞﾈｼｱﾙﾋﾟｱ | E116: IRP | F116: 0.0086 | G116: 円
C117: 台湾ﾄﾞﾙ | E117: TWD,NTD | F117: 2.82 | G117: 円
...

Sheet Sheet1
A1: 11年度 購入品標準原価 | F1: ※１ 購入単位あたり | G1: ※2 購入単位 = 単位換算 × BOM単位 （例： kg = 1000 × g)
A2: 品番 | B2: 品名 | C2: 購入先 | D2: 分類CD | E2: 購入単位 | F2: 標準単価 ※1 | G2: 単位換算 ※2 | H2: BOM単位 | I2: 大分類 | J2: 中分類 | K2: 小分類
A3: Q011749000-M00 | B3: 1013NW8(OUT) | C3: 古河産業株式会社 | D3: TA0 | E3: kg | F3: 355 | G3: 1000 | H3: g | I3: RESIN | J3: PA6 | K3: PA6
A4: T100111000-M00 | B4: 4359GN[NATURAL] | C4: 出光ライオンコンポジット株式会社 | D4: TA0 | E4: kg | F4: 325 | G4: 1000 | H4: g | I4: RESIN | J4: PP | K4: PP
A5: C010006000-M00 | B5: 446BU<KS>(BLUE)(RECEIVE) | C5: 古河産業株式会社 | D5: TA0 | E5: kg | F5: 1445 | G5: 1000 | H5: g | I5: COLOR RESIN | J5: MIE LOCAL | K5: MIE LOCAL
A6: N050004000-M20 | B6: 459YL<KS>(YELLOW)[J-JH] | C6: 古河産業株式会社 | D6: TA0 | E6: kg | F6: 1605 | G6: 1000 | H6: g | I6: RESIN | J6: COLOR BATCH | K6: COLOR BATCH
A7: P010163000-M00 | B7: 4600G-5(IN) | C7: 長瀬産業株式会社 | D7: TA0 | E7: kg | F7: 217.05 | G7: 1000 | H7: g | I7: RESIN | J7: PP | K7: PP
A8: P010163000-M70 | B8: 4600G-5(K9624) | C8: 長瀬産業株式会社 | D8: TA0 | E8: kg | F8: 217.05 | G8: 1000 | H8: g | I8: RESIN | J8: PP | K8: PP
A9: P010163000-M10 | B9: 4600G-5(OUT) | C9: 長瀬産業株式会社 | D9: TA0 | E9: kg | F9: 217.05 | G9: 1000 | H9: g | I9: RESIN | J9: PP | K9: PP
A10: P010163000-M50 | B10: 4600G-5(V-9031)(OUT) | C10: 長瀬産業株式会社 | D10: TA0 | E10: kg | F10: 217.05 | G10: 1000 | H10: g | I10: RESIN | J10: PP | K10: PP
A11: P010163000-M60 | B11: 4600G-5(V-9031)[J-FN] | C11: 長瀬産業株式会社 | D11: TA0 | E11: kg | F11: 217.05 | G11: 1000 | H11: g | I11: RESIN | J11: PP | K11: PP
A12: P010163000-M40 | B12: 4600G-5(V-9301)(IN) | C12: 長瀬産業株式会社 | D12: TA0 | E12: kg | F12: 217.05 | G12: 1000 | H12: g | I12: RESIN | J12: PP | K12: PP
A13: C010004000-M10 | B13: 464GN(KS)ﾐﾄﾞﾘ ﾐｴ(OUT) | C13: 古河産業株式会社 | D13: TA0 | E13: kg | F13: 1535 | G13: 1000 | H13: g | I13: COLOR RESIN | J13: MIE LOCAL | K13: MIE LOCAL
A14: C010004000-M00 | B14: 464GN(KS)ﾐﾄﾞﾘ ﾐｴ(RECEIVE) | C14: 古河産業株式会社 | D14: TA0 | E14: kg | F14: 1525 | G14: 1000 | H14: g | I14: COLOR RESIN | J14: MIE LOCAL | K14: MIE LOCAL
... A292: C030976000-M00 | B292: ﾚﾏﾛｲ(ﾌﾝｻｲ)ﾎｳｴｲ | C292: 宝永プラスチックス株式会社 | D292: TD0 | E292: kg | F292: 50 | G292: 1 | H292: kg | I292: MIE LOCAL | J292: MIE LOCAL | K292: MIE LOCAL

Sheet Sheet1 (2)
K1: CP-130278 別紙-1
A2: 030B向け検討コネクタ一覧
A5: 種類 | B5: 親番号 | C5: F/M | D5: assy名称（仮） | E5: 子番号 | F5: 構成部品 | G5: 部品名称（仮） | H5: 体積 mm3 | I5: 質量 ※2 g | J5: 材質 | K5: DWG No.
A7: 0.64Ⅱ-22P | B7: ① | C7: F | D7: XFSG-C-22F | E7: ①-1 | F7: HSG | G7: XFSG-E-22F | H7: 3418.5 | I7: 4.478 | J7: PBT B1305 | K7: XFSG-P-EF22-1
E8: ①-2 | F8: ﾘﾃｰﾅ | G8: XFSG-L-22N ※1 | H8: 386.3 | I8: 0.506 | J8: PBT B1305 | K8: XFSG-P-LN22-1
B9: ② | C9: M | D9: XFSG-C-22M | E9: ②-1 | F9: HSG | G9: XFSG-E-22M | H9: 5585.2 | I9: 7.317 | J9: PBT B1305 | K9: XFSG-P-EM22-1
E10: ②-2 | F10: ﾘﾃｰﾅ | G10: XFSG-L-22N ※1 | H10: 386.3 | I10: 0.506 | J10: PBT B1305 | K10: XFSG-P-LN22-1
A11: 0.64Ⅱ-10P+1.5-8P | B11: ③ | C11: F | D11: XFSG/FMG8-C-B18F | E11: ③-1 | F11: HSG | G11: XFSG/FMG8-E-B18F | H11: 3279.1 | I11: 4.296 | J11: PBT B1305 | K11: XFSFM-P-EF0818B-1
E12: ③-2 | F12: ﾘﾃｰﾅ | G12: XFSG/FMG8-L-B18F | H12: 365.3 | I12: 0.478 | J12: PBT B1305 | K12: XFSFM-P-LF0818B-1
B13: ④ | C13: M | D13: XFSG/FMG8-C-B18M | E13: ④-1 | F13: HSG | G13: XFSG/FMG8-E-B18M | H13: 6433.1 | I13: 8.427 | J13: PBT B1305 | K13: XFSFM-P-EM0818B-1
E14: ④-2 | F14: ﾘﾃｰﾅ | G14: XFSG/FMG8-L-B18M | H14: 398.8 | I14: 0.522 | J14: PBT B1305 | K14: XFSFM-P-LM0818B-1
A16: ※1 XFSG-L-22N は同一部品
A17: ※2 B1305 密度1310kg/m3 で計算

Sheet Sheet5
A1: 親番号 | B1: トヨタ品番 | C1: 720A使用数量/台 | D1: コネクタメーカー | E1: 12下期管理自給価格 | F1: 目標コスト（管理費込み） | G1: 720A償却個数（生涯）
A2: ① | B2: 90980-12372 | C2: 2 | D2: 住友電装 | E2: 11.1 | F2: =+E2*1.03 -> 11.433 | G2: =+C2*2025*12*6 -> 291600
A3: ② | B3: 90980-12371 | C3: 2 | D3: 住友電装 | E3: 14.2 | F3: =+E3*1.03 -> 14.626 | G3: =+C3*2025*12*6 -> 291600
A4: ③ | B4: 90980-12741 | C4: 2 | D4: 住友電装 | E4: 10.9 | F4: =+E4*1.03 -> 11.227 | G4: =+C4*2025*12*6 -> 291600
A5: ④ | B5: 90980-12740 | C5: 2 | D5: 住友電装 | E5: 13.6 | F5: =+E5*1.03 -> 14.008 | G5: =+C5*2025*12*6 -> 291600
A6: ⑤ | B6: 90980-12771 | C6: 4 | D6: 矢崎総業 | E6: 21.9 | F6: =+E6*1.03 -> 22.557 | G6: =+C6*2025*12*6 -> 583200
A7: ⑥ | B7: 90980-12770 | C7: 4 | D7: 矢崎総業 | E7: 24.3 | F7: =+E7*1.03 -> 25.029 | G7: =+C7*2025*12*6 -> 583200
A8: ⑦ | B8: 90980-12737 | C8: 1 | D8: 住友電装 | E8: 9.9 | F8: =+E8*1.03 -> 10.197 | G8: =+C8*2025*12*6 -> 145800
A9: ⑧ | B9: 90980-12736 | C9: 1 | D9: 住友電装 | E9: 11.7 | F9: =+E9*1.03 -> 12.051 | G9: =+C9*2025*12*6 -> 145800
A10: ⑨ | B10: 90980-12937 | C10: 1 | D10: 住友電装 | E10: 6.9 | F10: =+E10*1.03 -> 7.107 | G10: =+C10*2025*12*6 -> 145800
A11: ⑩ | B11: 90980-12936 | C11: 1 | D11: 住友電装 | E11: 8.4 | F11: =+E11*1.03 -> 8.652 | G11: =+C11*2025*12*6 -> 145800
A12: ⑪ | B12: 90980-12366 | C12: 1 | D12: 住友電装 | E12: 7.4 | F12: =+E12*1.03 -> 7.622 | G12: =+C12*2025*12*6 -> 145800
A13: ⑫ | B13: 90980-12365 | C13: 1 | D13: 住友電装 | E13: 8.8 | F13: =+E13*1.03 -> 9.064 | G13: =+C13*2025*12*6 -> 145800
... A15: ⑭ | B15: 90980-12807 | C15: 2 | D15: 住友電装 | E15: 9.3 | F15: =+E15*1.03 -> 9.579 | G15: =+C15*2025*12*6 -> 291600
B16: ※企画台数2,025台/月、6年モデルで算出
B17: ※目標コスト：最低限これ以下にしないといけないという数字

Sheet RESIN
A1: 10年度 購入品標準原価 | F1: ※１ 購入単位あたり | G1: ※2 購入単位 = 単位換算 × BOM単位 （例： kg = 1000 × g)
A2: 品番 | B2: 品名 | C2: 購入先 | D2: 分類CD | E2: 購入単位 | F2: 標準単価 ※1 | G2: 単位換算 ※2 | H2: BOM単位 | I2: 大分類 | J2: 中分類 | K2: 小分類
A3: Q011749000-M00 | B3: 1013NW8(OUT) | C3: 古河産業株式会社 | D3: TA0 | E3: kg | F3: 385 | G3: 1000 | H3: g | I3: RESIN | J3: PA6 | K3: PA6
A4: N050004000-M20 | B4: 459YL<KS>(YELLOW)[J-JH] | C4: 古河産業株式会社 | D4: TA0 | E4: kg | F4: 1605 | G4: 1000 | H4: g | I4: RESIN | J4: COLOR BATCH | K4: COLOR BATCH
A5: P010163000-M00 | B5: 4600G-5(IN) | C5: 長瀬産業株式会社 | D5: TA0 | E5: kg | F5: 209.55 | G5: 1000 | H5: g | I5: RESIN | J5: PP | K5: PP
A6: P010163000-M70 | B6: 4600G-5(K9624) | C6: 長瀬産業株式会社 | D6: TA0 | E6: kg | F6: 209.55 | G6: 1000 | H6: g | I6: RESIN | J6: PP | K6: PP
A7: P010163000-M10 | B7: 4600G-5(OUT) | C7: 長瀬産業株式会社 | D7: TA0 | E7: kg | F7: 209.55 | G7: 1000 | H7: g | I7: RESIN | J7: PP | K7: PP
A8: P010163000-M50 | B8: 4600G-5(V-9031)(OUT) | C8: 長瀬産業株式会社 | D8: TA0 | E8: kg | F8: 209.55 | G8: 1000 | H8: g | I8: RESIN | J8: PP | K8: PP
A9: P010163000-M60 | B9: 4600G-5(V-9031)[J-FN] | C9: 長瀬産業株式会社 | D9: TA0 | E9: kg | F9: 209.55 | G9: 1000 | H9: g | I9: RESIN | J9: PP | K9: PP
A10: P010163000-M40 | B10: 4600G-5(V-9301)(IN) | C10: 長瀬産業株式会社 | D10: TA0 | E10: kg | F10: 209.55 | G10: 1000 | H10: g | I10: RESIN | J10: PP | K10: PP
A11: P010164000-M00 | B11: 4704G | C11: 長瀬産業株式会社 | D11: TA0 | E11: kg | F11: 220.35 | G11: 1000 | H11: g | I11: RESIN | J11: PP | K11: PP
A12: R010410000-M10 | B12: CJ936N(J) | C12: 古河産業株式会社 | D12: TA0 | E12: kg | F12: 273 | G12: 1000 | H12: g | I12: RESIN | J12: PP | K12: PP
A13: R010410000-M00 | B13: CJ936N(OUT) [I] | C13: ＩＣＴＣ | D13: UG0 | E13: kg | F13: 89.04 | G13: 1000 | H13: g | I13: RESIN | J13: PP | K13: PP
A14: P030045000-M00 | B14: DELRIN 900P8(BLACK) | C14: ＣＢＣ株式会社 | D14: TA0 | E14: kg | F14: 225 | G14: 1000 | H14: g | I14: RESIN | J14: POM | K14: POM
... A207: C010042000-M00 | B207: ﾅｲﾛﾝｶﾗ- K 37-100(IN) | C207: 三井物産株式会社 | D207: TA0 | E207: kg | F207: 3050 | G207: 1000 | H207: g | I207: COLOR RESIN | J207: MIE LOCAL | K207: MIE LOCAL

Sheet 予算諸元表
A1: 09予算諸元表
B2: 諸元（部門）
C3: 部門 | E3: 部門コード | F3: 直間比 | G3: ＭＨ単価 | H3: ＭＴ単価 | I3: MPC
C4: AE実装 | E4: UBAE | F4: 1.21 | G4: 2225.9 | H4: 6900 | I4: AE作業組
C5: AE後工程 | E5: UBAF | F5: 1.21 | G5: 2225.9 | H5: 890.1 | I5: AE作業組
C6: AE MT無し | E6: UBM1 | F6: 1.21 | G6: 2225.9 | H6: 0 | I6: AE作業組 | J6: ←設備の無い工程
C7: AH多工程 | E7: UBAH | F7: 1.28 | G7: 2191.5 | H7: 2924.9 | I7: AH作業組
C8: AH単発 | E8: UBAI | F8: 1.28 | G8: 2191.5 | H8: 856.1 | I8: AH作業組
C9: AH MT0 | E9: UBM6 | F9: 1.28 | G9: 2191.5 | H9: 0 | I9: AH作業組 | J9: ←設備の無い工程
C10: AM組立 | E10: UBAM | F10: 1.18 | G10: 2169.2 | H10: 1128.5 | I10: AM作業組
C11: AM MT無し | E11: UBM2 | F11: 1.18 | G11: 2169.2 | H11: 0 | I11: AM作業組 | J11: ←設備の無い工程
C12: AS多工程 | E12: UBAS | F12: 1.7 | G12: 2228.9 | H12: 1083.7 | I12: AS作業組
C13: AS単発 | E13: UBAT | F13: 1.7 | G13: 2228.9 | H13: 1083.7 | I13: AS作業組
C14: AS MT無し | E14: UBM3 | F14: 1.7 | G14: 2228.9 | H14: 0 | I14: AS作業組 | J14: ←設備の無い工程
C15: JB成形 | E15: UBJB | F15: 1.18 | G15: 2901.5 | H15: 2076.7 | I15: JB作業組
C16: JB MT無し | E16: UBM0 | F16: 1.18 | G16: 2901.5 | H16: 0 | I16: JB作業組 | J16: ←設備の無い工程
C17: JC旧成形 | E17: UBJC | F17: 1.22 | G17: 2726.7 | H17: 1268.5 | I17: JC作業組
C18: JC新成形 | E18: UBJD | F18: 1.22 | G18: 2726.7 | H18: 1450.2 | I18: JC作業組
C19: JP400トンプレス | E19: UBJP | F19: 1.13 | G19: 2469.7 | H19: 5253.5 | I19: JP作業組
C20: JP高速プレス | E20: UBJQ | F20: 1.13 | G20: 2469.7 | H20: 3855.9 | I20: JP作業組
C21: JP積層プレス | E21: UBJR | F21: 1.13 | G21: 2469.7 | H21: 1850 | I21: JP作業組
C22: JSブロック | E22: UBJS | F22: 1.13 | G22: 1908.5 | H22: 2360.6 | I22: JS作業組
C23: JSコネクタ二次加工 | E23: UBJU | F23: 1.13 | G23: 1908.5 | H23: 362.6 | I23: JS作業組
C24: JS MT無し | E24: UBM4 | F24: 1.13 | G24: 1908.5 | H24: 0 | I24: JS作業組 | J24: ←設備の無い工程
C25: RBラミネート | E25: UBRF | F25: 1.14 | G25: 2397.9 | H25: 921.9 | I25: RB作業組
C26: RB束取 | E26: UBRG | F26: 1.14 | G26: 2397.9 | H26: 1549 | I26: RB作業組
C27: RB圧延 | E27: UBRP | F27: 1.14 | G27: 2397.9 | H27: 296.8 | I27: RB作業組
C28: RB MT無し | E28: UBM5 | F28: 1.14 | G28: 2397.9 | H28: 0 | I28: RB作業組 | J28: ←設備の無い工程
C29: RC | E29: UBRC | F29: 1.17 | G29: 1934.4 | H29: 1211.2 | I29: RC作業組
C30: 杉本電装（内作） | E30: UBSD | F30: 1 | G30: 0 | H30: 1793.3 | I30: 杉本電装（社内付）
C31: 保田産業（内作） | E31: UBYS | F31: 1 | G31: 0 | H31: 1636.6 | I31: 保田作業（社内付） | J31: ←梱包・選別・コネクタ組立など
C32: 再検査 | E32: UBRI | F32: 1 | G32: 0 | H32: 2662.2 | I32: 古河ライフ | J32: ←SRC再検査工程
B34: 諸元（間接費） ※全て対直原比率
C36: 間接費は、０8年の製品系統別PL予算より下記の値を用いる。
E37: ブロック | F37: ＳＲＣ | G37: コネクタ | H37: 電子部品※ | I37: センサー | J37: スマコネ | K37: アンテナ
C38: 工場間接費 | E38: 0.12048982 | F38: 0.11182968 | G38: 0.14694502 | H38: 0.11740127 | I38: 0.12043097 | J38: 0.07442975 | K38: 0.16410439
C39: 一般管理費 | E39: 0.091156534 | F39: 0.1086448 | G39: 0.15014259 | H39: 0.095504871 | I39: 0.083369917 | J39: 0.065985262 | K39: 0.14690259
C40: 営業外 | E40: 0.0028491943 | F40: 0.0028491943 | G40: 0.0028491943 | H40: 0.0028491943 | I40: 0.0028491943 | J40: 0.0028491943 | K40: 0.0028491943
E41: =SUM(E38:E40) -> 0.21449555 | F41: =SUM(F38:F40) -> 0.22332368 | G41: =SUM(G38:G40) -> 0.29993681 | H41: =SUM(H38:H40) -> 0.21575533 | I41: =SUM(I38:I40) -> 0.20665008 | J41: =SUM(J38:J40) -> 0.14326421 | K41: =SUM(K38:K40) -> 0.31385617
E42: (工場間接費は専用設備の償却費を除く｡) | I42: ※電装工場平均値
C43: ※工場間接費・一般管理費・営業外は、「日本に逆輸入する製品」に使用する「日供部材」の輸出には賦課しない。
C45: 販売直接費 | E45: ※国内の営業販直費は、SCを経由しない場合は０とし、工場販直費のみとする。
E46: 輸送費込み | H46: 輸送費別
C47: 国内 | E47: 営業販直 | F47: 工場販直 | G47: 計 | H47: 営業販直 | I47: 工場販直 | J47: 計
C48: SCを経由しない | E48: 0 | F48: 0.020389907 | G48: 0.020389907 | H48: 0 | I48: 0.011717697 | J48: 0.011717697
C49: マツダ | E49: 0.018475262 | F49: 0.020389907 | G49: 0.038865168 | H49: 0.018475262 | I49: 0.011717697 | J49: 0.030192959
C50: ダイハツ | E50: 0.0072241623 | F50: 0.020389907 | G50: 0.027614069 | H50: 0.0072241623 | I50: 0.011717697 | J50: 0.01894186
C51: ホンダ鈴鹿 | E51: 0.013556089 | F51: 0.020389907 | G51: 0.033945995 | H51: 0.013556089 | I51: 0.011717697 | J51: 0.025273786
C52: ホンダ狭山 | E52: 0.013725746 | F52: 0.020389907 | G52: 0.034115653 | H52: 0.013725746 | I52: 0.011717697 | J52: 0.025443444
C53: トヨタ | E53: 0.011550723 | F53: 0.020389907 | G53: 0.03194063 | H53: 0.011550723 | I53: 0.011717697 | J53: 0.02326842
C54: スズキ・ヤマハ | E54: 0.012449545 | F54: 0.020389907 | G54: 0.032839452 | H54: 0.012449545 | I54: 0.011717697 | J54: 0.024167242
C55: 富士重 | E55: 0.016478369 | F55: 0.020389907 | G55: 0.036868276 | H55: 0.016478369 | I55: 0.011717697 | J55: 0.028196066
C56: いすゞ | E56: 0.03969895 | F56: 0.020389907 | G56: 0.060088856 | H56: 0.03969895 | I56: 0.011717697 | J56: 0.051416647
E57: 輸送費込み | H57: 輸送費別
C58: 海外 | E58: 営業販直 | F58: 工場販直 | G58: 計 | H58: 営業販直 | I58: 工場販直 | J58: 計
C59: FEAP | E59: 0.03419846 | F59: 0.020389907 | G59: 0.054588367 | H59: 0 | I59: 0.011717697 | J59: 0.011717697
C60: FENA | E60: 0.038681033 | F60: 0.020389907 | G60: 0.05907094 | H60: 0 | I60: 0.011717697 | J60: 0.011717697
C61: FESZ | E61: 0.094639863 | F61: 0.020389907 | G61: 0.11502977 | H61: 0 | I61: 0.011717697 | J61: 0.011717697
C62: FAST | E62: 0.042927899 | F62: 0.020389907 | G62: 0.063317806 | H62: 0 | I62: 0.011717697 | J62: 0.011717697
C63: FACE | E63: 0.050640744 | F63: 0.020389907 | G63: 0.071030651 | H63: 0 | I63: 0.011717697 | J63: 0.011717697
C64: 津河 | E64: 0.040845553 | F64: 0.020389907 | G64: 0.061235459 | H64: 0 | I64: 0.011717697 | J64: 0.011717697
B66: ・古河電工本社費用
C67: ●古河電工と古河ASを連結して計算する場合の、電工本社費用の直原比率は下記を摘要します。
C68: 電工本社費用 | E68: 0.0025321235 | F68: （対直原比率） | H68: 古河電工側 一般管理費（事業部・営業部・本社）、社内利子
C69: ※古河AS単体での計算では使用しない。
B71: ・古河電工本社への口銭料
B72: ･古河電工への販売口銭率を08年度 5.31%→09年度 2%(海外関連5社向け1.5%; 2重口銭考慮)に変更
C74: 注文先 | D74: 口銭率
C75: FAS社内 | D75: 0
C76: FEAP | D76: 0.015
C77: FENA | D77: 0.015
C78: FESZ | D78: 0.015
C79: FAST | D79: 0.015
C80: 津河 | D80: 0.015
C81: 上記以外 | D81: 0.02
C82: ※ただし、客先売値に対する比率
B83: 客先売値に対し、上記の比率が口銭として差し引かれます。
C84: 「古河AS売値」 = (1-「口銭率」)×「古河電工売値（客先売値)」
B86: 09標準銅ベース | F86: 400 | G86: 円/KG
B88: 09標準為替レート
C89: 米ドル | E89: USD | F89: 95 | G89: 円
C90: ユ－ロ | E90: EUR | F90: 118 | G90: 円
C91: スターリングポンド | E91: GBP | F91: 138 | G91: 円
C92: 香港ドル | E92: HKD | F92: 12.3 | G92: 円
C93: シンガポールドル | E93: SGD | F93: 62.1 | G93: 円
C94: 中国元 | E94: CNY,RMB | F94: 13.9 | G94: 円
C95: タイバーツ | E95: THB | F95: 2.7 | G95: 円
C96: フィリピンペソ | E96: PHP | F96: 2 | G96: 円
C97: インドネシアルピア | E97: IRP | F97: 0.008 | G97: 円
C98: 台湾ドル | E98: TWD,NTD | F98: 2.9 | G98: 円
C99: 韓国ウォン | E99: KRW | F99: 0.065 | G99: 円
C100: ブラジルレアル | E100: BR | F100: 40.2 | G100: 円
... C104: マレーシアリンギ | E104: MYR | F104: 26.3 | G104: 円
B107: 海外拠点 見積り諸元 | F107: （2007年 海外事業推進室資料より）
J108: 日本円（標準為替レート）
C109: 拠点 | E109: 工程 | G109: ＭＨ単価 | H109: ＭＴ単価 | I109: 単位 | J109: ＭＨ単価 | K109: ＭＴ単価 | L109: 単位
C110: FURMEX(FENA) | E110: JPN SRC | G110: 3.28 | H110: 17.37 | I110: $/hour | J110: =G110*$F$89 -> 311.6 | K110: =H110*$F$89 -> 1650.15 | L110: \/hour
E111: USA SRC | G111: 2.07 | H111: 17.11 | I111: $/hour | J111: =G111*$F$89 -> 196.65 | K111: =H111*$F$89 -> 1625.45 | L111: \/hour
E112: GM ハーネス | G112: 3.23 | H112: 10.27 | I112: $/hour | J112: =G112*$F$89 -> 306.85 | K112: =H112*$F$89 -> 975.65 | L112: \/hour
E113: BOX組立 | G113: 4.16 | H113: 10.37 | I113: $/hour | J113: =G113*$F$89 -> 395.2 | K113: =H113*$F$89 -> 985.15 | L113: \/hour
...

Sheet Cost Table
B1: INJECTION PARTS | AW1: 間接費 13予算(FAS三重工場出荷品) | BA1: /海外工場出荷品(三重工場売上なし)提示なし | BF1: ※対直原比率 | BJ1: 営業販直費 13予算 | BP1: 工場販直費 13予算 ※対直原比率(三重工場から出荷する際）
U2: MT/MH | AX2: 工場 間接費 | AY2: 一般 管理費 | AZ2: 電工 本社費 | BB2: 工場 間接費 | BC2: 一般 管理費 | BD2: 電工 本社費 | BF2: 工場間接 | BG2: 一般管理 | BH2: 販直率 | BJ2: 行き先 | BK2: 輸送費 | BM2: 行き先 | BN2: 輸送費 | BS2: 輸送費 | BT2: 梱包費 | BU2: 出荷作業 | BV2: 工場販直
B3: quotation No. | U3: Process No. | V3: Process Name | AA3: Assign /machine | AB3: OA | AE3: Ratio Indirect-Direct/Direct | AF3: MH等価単価 | AG3: MT等価単価 | AH3: MH Charge | AI3: MT Charge | AJ3: Amortization | BK3: 込み | BL3: 別 | BN3: 込み | BO3: 別 | BP3: 1.全て直原比率で算出 | BS3: 0.0075 | BT3: 0.0077 | BU3: 0.0075 | BV3: 0.0227 | BW3: 1
B4: FOREX ( 1 PHP= ) | E4: 2.2 | L4: Resin | O4: FEAP | P4: FEAPsup | Q4: EPMI | AW4: ブロック | AX4: 0.042 | AY4: 0.0639 | AZ4: 0 | BB4: 0.0244 | BC4: 0.0823 | BD4: 0 | BE4: FURMEX | BF4: 0.138 | BG4: 0.128 | BH4: 0.016 | BI4: 対直原 | BJ4: SC経由なし | BK4: 0 | BM4: いすゞ | BN4: 0.0454 | BO4: - | BP4: 2.輸送費を別途計上 | BS4: 0 | BT4: 0.0077 | BU4: 0.0075 | BV4: 0.0153 | BW4: 2
B5: FOREX ( 1 USD= ) | E5: 105 | H5: SPS | L5: XAREX | U5: a | V5: FEAP Horizontal | AH5: =MTMH!E15 -> 297.65682 | AI5: =MTMH!E16 -> 543.66751 | AW5: SRC | AX5: 0.1369 | AY5: 0.1243 | AZ5: 0 | BB5: 0.0477 | BC5: 0.0732 | BD5: 0 | BE5: FACE | BF5: 0.128 | BG5: 0.082 | BH5: 0.065 | BI5: 対直原 | BJ5: マツダ | BK5: 0.007 | BM5: FEAP | BN5: 別途見積 | BO5: 0 | BP5: 3.輸送費・梱包費資材費を別途計上 | BS5: 0 | BT5: 0 | BU5: 0.0075 | BV5: =SUM(BS5:BU5) -> 0.0075 | BW5: 3 | CG5: For Horizontal Injection Process MT is Jpy 423
B6: Interest Rate (Annual) | E6: 0.02 | H6: PBT | L6: BASF B4520 Q120 | O6: ='Resin Recycle'!I5 -> 304.5 | U6: b | V6: FEAP Vertical | AH6: =AH5*2 -> 595.31365 | AI6: =MTMH!E17 -> 681.92075 | AW6: コネクタ | AX6: 0.1344 | AY6: 0.1025 | AZ6: 0 | BB6: 0.10454678 | BC6: 0.1397124 | BD6: 0 | BE6: FAST | BF6: 0.069 | BG6: 0.0766 | BH6: 0.058 | BI6: 対直原 | BJ6: ダイハツ | BK6: 0.0073 | BM6: FENA | BN6: 別途見積 | BO6: 0 | CG6: MH is Jpy 177
B7: Payment Term (months) | E7: 24 | H7: POM | L7: MEP F30-03 | O7: ='Resin Recycle'!I7 -> 207.9 | U7: c | V7: Off Line Work | AW7: 電子部品 | AX7: 0.071 | AY7: 0.0669 | AZ7: 0 | BB7: 0.0333 | BC7: 0.0822 | BD7: 0 | BE7: FEAP | BF7: 0.17 | BG7: 0.038 | BH7: 0.029 | BI7: 対直原 | BJ7: ホンダ鈴鹿 | BK7: 0.0145 | BM7: FESZ | BN7: 別途見積 | BO7: 0
B8: Start to Investment | E8: - | H8: POM | L8: MEP F30-73R1 | O8: ='Resin Recycle'!F8 -> 345.5 | U8: d | V8: BSS Vertical | BE8: FESZ | BF8: 0.092 | BG8: 0.057 | BH8: 0.042 | BI8: 対直原 | BJ8: ホンダ狭山 | BK8: 0.0145 | BM8: FAST | BN8: 別途見積 | BO8: 0
B9: Start to mass prod. | E9: - | H9: POM | L9: MEP FX-11J | O9: ='Resin Recycle'!I10 -> 417.9 | U9: e | AW9: スマコネ | AX9: 0.0404 | AY9: 0.0697 | AZ9: 0 | BB9: 0.0198 | BC9: 0.0748 | BD9: 0 | BE9: 津河 | BF9: 0.1 | BG9: 0.07 | BH9: 0.02 | BI9: 対直原 | BJ9: トヨタ | BK9: 0.0098 | BM9: FACE | BN9: 別途見積 | BO9: 0
B10: Operetion Hour (Hr/Day) | E10: 24 | H10: PPS | L10: DIC FZ-1140K | O10: ='Resin Recycle'!F23 -> 736.5 | U10: f | BB10: 0.0472 | BC10: 0 | BD10: 0 | BE10: FAPV | BF10: 0.1735 | BG10: 0.0776 | BI10: 対加工費 | BJ10: スズキ・ヤマハ | BK10: 0.0169 | BM10: 津河 | BN10: 別途見積 | BO10: 0
B11: Operational Availability(%) | E11: 0.95 | H11: PPS | L11: DIC FZ-1040K | O11: ='Resin Recycle'!F24 -> 776.9 | U11: g | AW11: 営業外 | AX11: 0.0028 | BE11: ※1減価償却費含む | BJ11: 富士重 | BK11: 0.0169 | BN11: ※海外輸送費は, 各拠点毎のﾌｫ-ﾏｯﾄで算出の事。
B13: Injection Molding Parts, Direct Cost
B14: QuotationNo. | C14: Process No. | E14: Process Name | H14: Demand | I14: Ave.Days | J14: Daily | K14: Lot Size | M14: Loss Rate | P14: Resin Name | S14: # Of Cavity | T14: Single Shot Inf. | X14: Production Lot | Z14: Resin | AA14: Recycle | AB14: Recycle | AC14: Disposal | AE14: Material Cost (JPY/pcs) | AF14: Cycle Time (sec) | AG14: Process Cost | AL14: Purge Loss | AN14: Prod. loss (defect) | AQ14: Operational Availability
H15: Ave. | I15: / Month | J15: Demand | M15: Purge (%) | N15: Disposal (%) | O15: Defect (%) | T15: Parts | U15: Runner | V15: Consum- | X15: Prdn | Y15: Consum- | Z15: Cost | AA15: Ratio | AB15: Cost | AC15: Cost | AG15: Man/Machine | AI15: PC | AN15: Intial | AO15: QC | AP15: Total | AQ15: change | AR15: OA (%)
V16: ption | X16: Shots | Y16: ption | AG16: Charge Rate (JPY/H) | AN16: Disposal | AO16: Sample | AQ16: model
H17: pcs/M | I17: Y2020 | K17: (Pcs/time) | P17: Polymer | Q17: Grade | T17: g/pc | U17: g/shot | V17: g/shot | X17: shots/Lot | Y17: g/pc | Z17: JPY/Kg | AA17: % | AB17: JPY/Kg | AC17: JPY/Kg | AD17: JPY/pc | AG17: MH | AH17: MT | AI17: （JPY/pc） | AL17: g/Lot | AM17: Shots/Lot | AN17: Shots/Lot | AO17: Shots/Lot | AP17: g/Lot | AQ17: min
B18: 1 | C18: a | D18: TMR-050 | E18: ROTAOTR | K18: 20000 | M18: =AM18*S18/K18 -> 0.0012578616 | N18: =(AN18+AO18)*S18/K18 -> 0.0018 | O18: 0.0002 | P18: POM | Q18: FX-11J | S18: 2 | T18: 31.6 | U18: 16.3 | V18: =T18*S18+U18 -> 79.5 | X18: =ROUNDUP((K18/(1-O18)+AN18+AO18)/S18,0) -> 10012 | Y18: =(X18*V18+AL18)/K18 -> 39.8477 | Z18: 437.8 | AA18: 0 | AB18: ='Resin Recycle'!$O$48 -> 57.114983 | AC18: =IF(AA18=0,'Resin Recycle'!$F$40,0) -> 17.6 | AD18: =(Y18-T18)*AC18/1000 -> 0.14515952 | AE18: =Y18*(1-AA18)*Z18/1000+Y18*AA18*AB18/1000+AD18 -> 17.590483 | AF18: 30 | AG18: =AH$5 -> 297.65682 | AH18: =AI$5 -> 543.66751 | AI18: =ROUNDUP(AF18/S18*(AH18+AG18)/(1-N18-O18)/3600,2) -> 3.52 | AL18: 1000 | AM18: =AL18/V18 -> 12.578616 | AN18: 15 | AO18: 3 | AP18: =(AN18+AO18)*V18 -> 1431 | AQ18: 30 | AR18: =IF(C18<1," ",(K18*AF18/S18)/(AQ18*60+K18*AF18/S18)) -> 0.99403579
B19: 2 | C19: a | D19: TMR-051 | E19: STATOR | K19: 20000 | M19: =AM19*S19/K19 -> 0.0012578616 | N19: =(AN19+AO19)*S19/K19 -> 0.0018 | O19: 0.0002 | P19: PBT | Q19: BASF B4520 Q120 | S19: 2 | T19: 31.6 | U19: 16.3 | V19: =T19*S19+U19 -> 79.5 | X19: =ROUNDUP((K19/(1-O19)+AN19+AO19)/S19,0) -> 10012 | Y19: =(X19*V19+AL19)/K19 -> 39.8477 | Z19: 437.8 | AA19: 0 | AB19: ='Resin Recycle'!$O$48 -> 57.114983 | AC19: =IF(AA19=0,'Resin Recycle'!$F$40,0) -> 17.6 | AD19: =(Y19-T19)*AC19/1000 -> 0.14515952 | AE19: =Y19*(1-AA19)*Z19/1000+Y19*AA19*AB19/1000+AD19 -> 17.590483 | AF19: 30 | AG19: =AH$5 -> 297.65682 | AH19: =AI$5 -> 543.66751 | AI19: =ROUNDUP(AF19/S19*(AH19+AG19)/(1-N19-O19)/3600,2) -> 3.52 | AL19: 1000 | AM19: =AL19/V19 -> 12.578616 | AN19: 15 | AO19: 3 | AP19: =(AN19+AO19)*V19 -> 1431 | AQ19: 30 | AR19: =IF(C19<1," ",(K19*AF19/S19)/(AQ19*60+K19*AF19/S19)) -> 0.99403579
B20: 3 | C20: a | D20: TMR-051 | E20: SUBSTATOR | K20: 20000 | M20: =AM20*S20/K20 -> 0.0012578616 | N20: =(AN20+AO20)*S20/K20 -> 0.0018 | O20: 0.0002 | P20: PPE+PA | Q20: C82HL | S20: 2 | T20: 31.6 | U20: 16.3 | V20: =T20*S20+U20 -> 79.5 | X20: =ROUNDUP((K20/(1-O20)+AN20+AO20)/S20,0) -> 10012 | Y20: =(X20*V20+AL20)/K20 -> 39.8477 | Z20: 437.8 | AA20: 0 | AB20: ='Resin Recycle'!$O$48 -> 57.114983 | AC20: =IF(AA20=0,'Resin Recycle'!$F$40,0) -> 17.6 | AD20: =(Y20-T20)*AC20/1000 -> 0.14515952 | AE20: =Y20*(1-AA20)*Z20/1000+Y20*AA20*AB20/1000+AD20 -> 17.590483 | AF20: 29 | AG20: =AH$5 -> 297.65682 | AH20: =AI$5 -> 543.66751 | AI20: =ROUNDUP(AF20/S20*(AH20+AG20)/(1-N20-O20)/3600,2) -> 3.4 | AL20: 1000 | AM20: =AL20/V20 -> 12.578616 | AN20: 15 | AO20: 3 | AP20: =(AN20+AO20)*V20 -> 1431 | AQ20: 30 | AR20: =IF(C20<1," ",(K20*AF20/S20)/(AQ20*60+K20*AF20/S20)) -> 0.99383139
B21: 4 | C21: a | D21: TMR-051 | E21: SLEEVE | K21: 20000 | M21: =AM21*S21/K21 -> 0.0012578616 | N21: =(AN21+AO21)*S21/K21 -> 0.0018 | O21: 0.0002 | P21: PPE+PA | Q21: C82HL | S21: 2 | T21: 31.6 | U21: 16.3 | V21: =T21*S21+U21 -> 79.5 | X21: =ROUNDUP((K21/(1-O21)+AN21+AO21)/S21,0) -> 10012 | Y21: =(X21*V21+AL21)/K21 -> 39.8477 | Z21: 437.8 | AA21: 0.2 | AB21: ='Resin Recycle'!$O$48 -> 57.114983 | AC21: =IF(AA21=0,'Resin Recycle'!$F$40,0) -> 0 | AD21: =(Y21-T21)*AC21/1000 -> 0 | AE21: =Y21*(1-AA21)*Z21/1000+Y21*AA21*AB21/1000+AD21 -> 14.411439 | AF21: 29 | AG21: =AH$5 -> 297.65682 | AH21: =AI$5 -> 543.66751 | AI21: =ROUNDUP(AF21/S21*(AH21+AG21)/(1-N21-O21)/3600,2) -> 3.4 | AL21: 1000 | AM21: =AL21/V21 -> 12.578616 | AN21: 15 | AO21: 3 | AP21: =(AN21+AO21)*V21 -> 1431 | AQ21: 30 | AR21: =IF(C21<1," ",(K21*AF21/S21)/(AQ21*60+K21*AF21/S21)) -> 0.99383139
B22: 5 | C22: a | D22: TMR-051 | E22: MOLDHOLDER 1 | K22: 20000 | M22: =AM22*S22/K22 -> 0.0012578616 | N22: =(AN22+AO22)*S22/K22 -> 0.0018 | O22: 0.0002 | P22: PBT | Q22: BASF B4520 Q120 | S22: 2 | T22: 31.6 | U22: 16.3 | V22: =T22*S22+U22 -> 79.5 | X22: =ROUNDUP((K22/(1-O22)+AN22+AO22)/S22,0) -> 10012 | Y22: =(X22*V22+AL22)/K22 -> 39.8477 | Z22: 437.8 | AA22: 0.2 | AB22: ='Resin Recycle'!$O$48 -> 57.114983 | AC22: =IF(AA22=0,'Resin Recycle'!$F$40,0) -> 0 | AD22: =(Y22-T22)*AC22/1000 -> 0 | AE22: =Y22*(1-AA22)*Z22/1000+Y22*AA22*AB22/1000+AD22 -> 14.411439 | AF22: 28 | AG22: =AH$5 -> 297.65682 | AH22: =AI$5 -> 543.66751 | AI22: =ROUNDUP(AF22/S22*(AH22+AG22)/(1-N22-O22)/3600,2) -> 3.28 | AL22: 1000 | AM22: =AL22/V22 -> 12.578616 | AN22: 15 | AO22: 3 | AP22: =(AN22+AO22)*V22 -> 1431 | AQ22: 30 | AR22: =IF(C22<1," ",(K22*AF22/S22)/(AQ22*60+K22*AF22/S22)) -> 0.99361249
B23: 6 | C23: a | D23: TMR-051 | E23: MOLDHOLDER 2 | K23: 20000 | M23: =AM23*S23/K23 -> 0.0012578616 | N23: =(AN23+AO23)*S23/K23 -> 0.0018 | O23: 0.0002 | P23: PBT | Q23: BASF B4520 Q120 | S23: 2 | T23: 31.6 | U23: 16.3 | V23: =T23*S23+U23 -> 79.5 | X23: =ROUNDUP((K23/(1-O23)+AN23+AO23)/S23,0) -> 10012 | Y23: =(X23*V23+AL23)/K23 -> 39.8477 | Z23: 437.8 | AA23: 0.15 | AB23: ='Resin Recycle'!$O$48 -> 57.114983 | AC23: =IF(AA23=0,'Resin Recycle'!$F$40,0) -> 0 | AD23: =(Y23-T23)*AC23/1000 -> 0 | AE23: =Y23*(1-AA23)*Z23/1000+Y23*AA23*AB23/1000+AD23 -> 15.16991 | AF23: 28 | AG23: =AH$5 -> 297.65682 | AH23: =AI$5 -> 543.66751 | AI23: =ROUNDUP(AF23/S23*(AH23+AG23)/(1-N23-O23)/3600,2) -> 3.28 | AL23: 1000 | AM23: =AL23/V23 -> 12.578616 | AN23: 15 | AO23: 3 | AP23: =(AN23+AO23)*V23 -> 1431 | AQ23: 30 | AR23: =IF(C23<1," ",(K23*AF23/S23)/(AQ23*60+K23*AF23/S23)) -> 0.99361249
B24: 7
B25: 8
B26: 9
B27: 10
B28: 11
B29: 12
B30: 13
B31: 14
B32: 15
AQ33: Stop-Start
B34: Other Direct Cost
B35: =B14 -> QuotationNo. | D35: Anneal Process Cost | H35: Parts Cost （JPY/pcs）
D36: Anneal process | E36: Cost | F36: Defect | G36: Cost | H36: material | I36: process | J36: Direct Cost （JPY/pc)
E38: JPY/pc | F38: Rate (%) | G38: JPY/pc
B39: =B18 -> 1 | D39: YES | E39: 1.7146735 | F39: 0.005 | G39: =E39/(1-F39) -> 1.72329 | H39: =AE18 -> 17.590483 | I39: =G39+AI18 -> 5.24329 | J39: =IF(C18<1," ",H39+I39) -> 22.833773
B40: =B19 -> 2 | D40: YES | E40: 1.7381521 | F40: 0.005 | G40: =E40/(1-F40) -> 1.7468865 | H40: =AE19 -> 17.590483 | I40: =G40+AI19 -> 5.2668865 | J40: =IF(C19<1," ",H40+I40) -> 22.857369 | CB40: 入り数検討
B41: =B20 -> 3 | D41: YES | E41: 4.1306663 | F41: 0.005 | G41: =E41/(1-F41) -> 4.1514234 | H41: =AE20 -> 17.590483 | I41: =G41+AI20 -> 7.5514234 | J41: =IF(C20<1," ",H41+I41) -> 25.141906 | CB41: ポリ内寸 | CC41: 製品 | CD41: 入り数
B42: =B21 -> 4 | D42: NO | E42: 1.6522665 | F42: 0.005 | G42: =E42/(1-F42) -> 1.6605694 | H42: =AE21 -> 14.411439 | I42: =G42+AI21 -> 5.0605694 | J42: =IF(C21<1," ",H42+I42) -> 19.472008 | CB42: 642 | CC42: 100 | CD42: =CB42/CC42 -> 6.42
B43: =B22 -> 5 | D43: NO | E43: 7.8838623 | F43: 0.005 | G43: =E43/(1-F43) -> 7.9234797 | H43: =AE22 -> 14.411439 | I43: =G43+AI22 -> 11.20348 | J43: =IF(C22<1," ",H43+I43) -> 25.614918 | CB43: 342 | CC43: 180 | CD43: =CB43/CC43 -> 1.9
B44: =B23 -> 6 | D44: NO | E44: 7.8838623 | F44: 0.005 | G44: =E44/(1-F44) -> 7.9234797 | H44: =AE23 -> 15.16991 | I44: =G44+AI23 -> 11.20348 | J44: =IF(C23<1," ",H44+I44) -> 26.373389 | CB44: 204 | CC44: 25 | CD44: =CB44/CC44 -> 8.16
B45: =B24 -> 7
B46: =B25 -> 8
B47: =B26 -> 9
B48: =B27 -> 10
B49: =B28 -> 11
B50: =B29 -> 12
B51: =B30 -> 13
B52: =B31 -> 14
B53: =B32 -> 15
AW55: in house packing and shipping cost
AL56: 管理費率（％） | AN56: 検査・梱包費 | AU56: 輸送費 （外注→工場） | AW56: packing material cost | BE56: packing process cost | BI56: 輸送費
AN57: 入数 （個/箱） | AO57: 資材費 | AR57: チャージ（円/hr) | AS57: タクト(sec） | AT57: 梱包費 （円/個） | AW57: box （円/個） | AX57: partition | AZ57: pad | BB57: other | BD57: total （円/個） | BE57: charge（円/hr) | BF57: tact time（sec) | BH57: total （円/個） | BI57: transfer | BJ57: total
AO58: （円/箱） | AQ58: （円/個） | AU58: （円/箱） | AV58: （円/個） | AX58: （円/個） | AY58: 個数 | AZ58: （円/個） | BA58: 個数 | BB58: （円/個） | BC58: 個数 | BF58: packing | BG58: assemble | BI58: 円/箱 | BJ58: 円/個 | BM58: palet | BN58: corton | BO58: poly box | BP58: price
AL59: 0.2 | AN59: 3000 | AO59: =1.15*$E$5 -> 120.75 | AQ59: =AO59/AN59 -> 0.04025 | AR59: 354 | AS59: 180 | AT59: =IF(#REF!="N"," ",AR59*AS59/3600)/AN59 -> #REF! | AU59: 0 | AV59: 0 | AW59: 70 | AX59: 5 | AY59: 0 | AZ59: 3 | BA59: 2 | BB59: 10 | BC59: 1 | BD59: =(AW59+AX59*AY59+AZ59*BA59+BB59*BC59)/Z59/AN59 -> #DIV/0! | BE59: =AH7 -> 0 | BF59: 900 | BG59: 71.41 | BH59: =IF(Z59<1," ",BE59*(BF59+BG59/Z59)/3600)/AN59 -> #VALUE! | BI59: =BP59/BN59/BM59 -> #REF! | BJ59: =IF(Z59<1," ",BI59/Z59)/AN59 -> #VALUE! | BL59: 20f | BM59: 24 | BN59: 24 | BP59: =(BN21*E5+#REF!*5450)*(1+BW21) -> #REF! | BQ59: JPY/times
AL60: 0.2 | AN60: 3000 | AO60: =1.15*$E$5 -> 120.75 | AQ60: =AO60/AN60 -> 0.04025 | AR60: 354 | AS60: 180 | AT60: =IF(#REF!="N"," ",AR60*AS60/3600)/AN60 -> #REF! | AU60: 0 | AV60: 0 | AW60: 70 | AX60: 5 | AY60: 0 | AZ60: 3 | BA60: 2 | BB60: 10 | BC60: 1 | BD60: =(AW60+AX60*AY60+AZ60*BA60+BB60*BC60)/Z60/AN60 -> #DIV/0! | BE60: =BE59 -> 0 | BF60: 900 | BG60: 71.41 | BH60: =IF(Z60<1," ",BE60*(BF60+BG60/Z60)/3600)/AN60 -> #VALUE! | BI60: =BI59 -> #REF! | BJ60: =IF(Z60<1," ",BI60/Z60)/AN60 -> #VALUE! | BL60: 40f
AL61: 0.2 | AN61: 3000 | AO61: =1.15*$E$5 -> 120.75 | AQ61: =AO61/AN61 -> 0.04025 | AR61: 354 | AS61: 180 | AT61: =IF(#REF!="N"," ",AR61*AS61/3600)/AN61 -> #REF! | AU61: 0 | AV61: 0 | AW61: 70 | AX61: 5 | AY61: 0 | AZ61: 3 | BA61: 2 | BB61: 10 | BC61: 1 | BD61: =(AW61+AX61*AY61+AZ61*BA61+BB61*BC61)/Z61/AN61 -> #DIV/0! | BE61: =BE60 -> 0 | BF61: 900 | BG61: 71.41 | BH61: =IF(Z61<1," ",BE61*(BF61+BG61/Z61)/3600)/AN61 -> #VALUE! | BI61: =BI60 -> #REF! | BJ61: =IF(Z61<1," ",BI61/Z61)/AN61 -> #VALUE!
AL62: 0.2 | AQ62: 0 | AT62: =IF(#REF!="N"," ",AR62*AS62/3600) -> #REF! | AV62: 0 | BD62: =(AW62+AX62*AY62+AZ62*BA62+BB62*BC62)/Z62 -> #DIV/0! | BH62: =IF(Z62<1," ",BE62*(BF62+BG62/Z62)/3600) | BJ62: =IF(Z62<1," ",BI62/Z62)
AL63: 0.2 | AQ63: 0 | AT63: =IF(#REF!="N"," ",AR63*AS63/3600) -> #REF! | AV63: 0 | BD63: =(AW63+AX63*AY63+AZ63*BA63+BB63*BC63)/Z63 -> #DIV/0! | BH63: =IF(Z63<1," ",BE63*(BF63+BG63/Z63)/3600) | BJ63: =IF(Z63<1," ",BI63/Z63)
AL64: 0.2 | AQ64: 0 | AT64: =IF(#REF!="N"," ",AR64*AS64/3600) -> #REF! | AV64: 0 | BD64: =(AW64+AX64*AY64+AZ64*BA64+BB64*BC64)/Z64 -> #DIV/0! | BH64: =IF(Z64<1," ",BE64*(BF64+BG64/Z64)/3600) | BJ64: =IF(Z64<1," ",BI64/Z64)
AL73: 12.12 | AT73: =IF(#REF!="N"," ",AR73*AS73/3600) -> #REF! | AU73: 0 | AV73: =IF(#REF!="N"," ",AU73/AN73) -> #REF! | AW73: 70 | AX73: 5 | AY73: 1 | AZ73: 3 | BA73: 2 | BD73: =(AW73+AX73*AY73+AZ73*BA73+BB73*BC73)/Z73 -> #DIV/0! | BE73: =0.954*90 -> 85.86 | BF73: 1.5 | BG73: 71.41 | BH73: =IF(Z73<1," ",BE73*(BF73+BG73/Z73)/3600) | BJ73: =IF(Z73<1," ",BI73/Z73)
AL74: 13.12 | AT74: =IF(#REF!="N"," ",AR74*AS74/3600) -> #REF! | AU74: 0 | AV74: =IF(#REF!="N"," ",AU74/AN74) -> #REF! | AW74: 70 | AX74: 5 | AY74: 1 | AZ74: 3 | BA74: 2 | BD74: =(AW74+AX74*AY74+AZ74*BA74+BB74*BC74)/Z74 -> #DIV/0! | BE74: =0.954*90 -> 85.86 | BF74: 1.5 | BG74: 71.41 | BH74: =IF(Z74<1," ",BE74*(BF74+BG74/Z74)/3600) | BJ74: =IF(Z74<1," ",BI74/Z74)
AL75: 14.12 | AT75: =IF(#REF!="N"," ",AR75*AS75/3600) -> #REF! | AU75: 0 | AV75: =IF(#REF!="N"," ",AU75/AN75) -> #REF! | AW75: 70 | AX75: 5 | AY75: 1 | AZ75: 3 | BA75: 2 | BD75: =(AW75+AX75*AY75+AZ75*BA75+BB75*BC75)/Z75 -> #DIV/0! | BE75: =0.954*90 -> 85.86 | BF75: 1.5 | BG75: 71.41 | BH75: =IF(Z75<1," ",BE75*(BF75+BG75/Z75)/3600) | BJ75: =IF(Z75<1," ",BI75/Z75)
AL76: 15.12 | AQ76: =IF(#REF!="N"," ",AO76/AN76) -> #REF! | AT76: =IF(#REF!="N"," ",AR76*AS76/3600) -> #REF! | AU76: 0 | AV76: =IF(#REF!="N"," ",AU76/AN76) -> #REF! | AW76: 70 | AX76: 5 | AY76: 1 | AZ76: 3 | BA76: 2 | BD76: =(AW76+AX76*AY76+AZ76*BA76+BB76*BC76)/Z76 -> #DIV/0! | BE76: =0.954*90 -> 85.86 | BF76: 1.5 | BG76: 71.41 | BH76: =IF(Z76<1," ",BE76*(BF76+BG76/Z76)/3600) | BJ76: =IF(Z76<1," ",BI76/Z76)
AL77: 16.12 | AQ77: =IF(#REF!="N"," ",AO77/AN77) -> #REF! | AT77: =IF(#REF!="N"," ",AR77*AS77/3600) -> #REF! | AU77: 0 | AV77: =IF(#REF!="N"," ",AU77/AN77) -> #REF! | AW77: 70 | AX77: 5 | AY77: 1 | AZ77: 3 | BA77: 2 | BD77: =(AW77+AX77*AY77+AZ77*BA77+BB77*BC77)/Z77 -> #DIV/0! | BE77: =0.954*90 -> 85.86 | BF77: 1.5 | BG77: 71.41 | BH77: =IF(Z77<1," ",BE77*(BF77+BG77/Z77)/3600) | BJ77: =IF(Z77<1," ",BI77/Z77)
AL78: 17.12 | AQ78: =IF(#REF!="N"," ",AO78/AN78) -> #REF! | AT78: =IF(#REF!="N"," ",AR78*AS78/3600) -> #REF! | AU78: 0 | AV78: =IF(#REF!="N"," ",AU78/AN78) -> #REF! | AW78: 70 | AX78: 5 | AY78: 1 | AZ78: 3 | BA78: 2 | BD78: =(AW78+AX78*AY78+AZ78*BA78+BB78*BC78)/Z78 -> #DIV/0! | BE78: =0.954*90 -> 85.86 | BF78: 1.5 | BG78: 71.41 | BH78: =IF(Z78<1," ",BE78*(BF78+BG78/Z78)/3600) | BJ78: =IF(Z78<1," ",BI78/Z78)
AL79: 18.12 | AQ79: =IF(#REF!="N"," ",AO79/AN79) -> #REF! | AT79: =IF(#REF!="N"," ",AR79*AS79/3600) -> #REF! | AU79: 0 | AV79: =IF(#REF!="N"," ",AU79/AN79) -> #REF! | AW79: 70 | AX79: 5 | AY79: 1 | AZ79: 3 | BA79: 2 | BD79: =(AW79+AX79*AY79+AZ79*BA79+BB79*BC79)/Z79 -> #DIV/0! | BE79: =0.954*90 -> 85.86 | BF79: 1.5 | BG79: 71.41 | BH79: =IF(Z79<1," ",BE79*(BF79+BG79/Z79)/3600) | BJ79: =IF(Z79<1," ",BI79/Z79)
AL80: 19.12 | AQ80: =IF(#REF!="N"," ",AO80/AN80) -> #REF! | AT80: =IF(#REF!="N"," ",AR80*AS80/3600) -> #REF! | AU80: 0 | AV80: =IF(#REF!="N"," ",AU80/AN80) -> #REF! | AW80: 70 | AX80: 5 | AY80: 1 | AZ80: 3 | BA80: 2 | BD80: =(AW80+AX80*AY80+AZ80*BA80+BB80*BC80)/Z80 -> #DIV/0! | BE80: =0.954*90 -> 85.86 | BF80: 1.5 | BG80: 71.41 | BH80: =IF(Z80<1," ",BE80*(BF80+BG80/Z80)/3600) | BJ80: =IF(Z80<1," ",BI80/Z80)
AL81: 20.12
AL82: 21.12
AL83: 22.12
AL84: 23.12 | AQ84: =IF(#REF!="N"," ",AO84/AN84) -> #REF! | AT84: =IF(#REF!="N"," ",AR84*AS84/3600) -> #REF! | AU84: 0 | AV84: =IF(#REF!="N"," ",AU84/AN84) -> #REF! | AW84: 70 | AX84: 5 | AY84: 1 | AZ84: 3 | BA84: 2 | BD84: =(AW84+AX84*AY84+AZ84*BA84+BB84*BC84)/Z84 -> #DIV/0! | BE84: =0.954*90 -> 85.86 | BF84: 1.5 | BG84: 71.41 | BH84: =IF(Z84<1," ",BE84*(BF84+BG84/Z84)/3600) | BJ84: =IF(Z84<1," ",BI84/Z84)
AQ86: 1Cavあたりの製作費 | AT86: 金型部品費 （千円） | BC86: 金型費合計 （千円）
AL87: 購入部品 | AN87: ホット ランナー | AO87: その他 | AQ87: 本体 加工費 | AR87: 組付調整 | AS87: 寸法測定 | AT87: スライド1 | AU87: スライド2 | AV87: 形状1 | AW87: 形状2 | AX87: 形状3 | AY87: 形状4 | AZ87: 形状5 | BA87: 形状6 | BB87: 形状7 | BC87: 製作代 合計 | BD87: メーカー利益 | BF87: 総合計
AT88: 400 | AU88: 75 | BD88: （％） | BE88: （千円）
BC89: =SUM(AL89:AO89)+(AR89+AS89+AQ89+(AT$88*AT89+AU$88*AU89+AV$88*AV89+AW$88*AW89+AX$88*AX89+AY$88*AY89+AZ$88*AZ89+BA$88*BA89+BB$88*BB89))*S18 -> 0 | BE89: =BC89*BD89 -> 0 | BF89: =BC89+BE89 -> 0
BC90: =SUM(AL90:AO90)+(AR90+AS90+AQ90+(AT$88*AT90+AU$88*AU90+AV$88*AV90+AW$88*AW90+AX$88*AX90+AY$88*AY90+AZ$88*AZ90+BA$88*BA90+BB$88*BB90))*S19 -> 0 | BE90: =BC90*BD90 -> 0 | BF90: =BC90+BE90 -> 0
BC91: =SUM(AL91:AO91)+(AR91+AS91+AQ91+(AT$88*AT91+AU$88*AU91+AV$88*AV91+AW$88*AW91+AX$88*AX91+AY$88*AY91+AZ$88*AZ91+BA$88*BA91+BB$88*BB91))*S20 -> 0 | BE91: =BC91*BD91 -> 0 | BF91: =BC91+BE91 -> 0
BC92: =SUM(AL92:AO92)+(AR92+AS92+AQ92+(AT$88*AT92+AU$88*AU92+AV$88*AV92+AW$88*AW92+AX$88*AX92+AY$88*AY92+AZ$88*AZ92+BA$88*BA92+BB$88*BB92))*S21 -> 0 | BE92: =BC92*BD92 -> 0 | BF92: =BC92+BE92 -> 0
BC93: =SUM(AL93:AO93)+(AR93+AS93+AQ93+(AT$88*AT93+AU$88*AU93+AV$88*AV93+AW$88*AW93+AX$88*AX93+AY$88*AY93+AZ$88*AZ93+BA$88*BA93+BB$88*BB93))*S23 -> 0 | BE93: =BC93*BD93 -> 0 | BF93: =BC93+BE93 -> 0
BC102: =SUM(AL102:AO102)+(AR102+AS102+AQ102+(AT$88*AT102+AU$88*AU102+AV$88*AV102+AW$88*AW102+AX$88*AX102+AY$88*AY102+AZ$88*AZ102+BA$88*BA102+BB$88*BB102))*#REF! -> #REF! | BE102: =BC102*BD102 -> #REF! | BF102: =BC102+BE102 -> #REF!
BC103: =SUM(AL103:AO103)+(AR103+AS103+AQ103+(AT$88*AT103+AU$88*AU103+AV$88*AV103+AW$88*AW103+AX$88*AX103+AY$88*AY103+AZ$88*AZ103+BA$88*BA103+BB$88*BB103))*#REF! -> #REF! | BE103: =BC103*BD103 -> #REF! | BF103: =BC103+BE103 -> #REF!
BC104: =SUM(AL104:AO104)+(AR104+AS104+AQ104+(AT$88*AT104+AU$88*AU104+AV$88*AV104+AW$88*AW104+AX$88*AX104+AY$88*AY104+AZ$88*AZ104+BA$88*BA104+BB$88*BB104))*#REF! -> #REF! | BE104: =BC104*BD104 -> #REF! | BF104: =BC104+BE104 -> #REF!
BC105: =SUM(AL105:AO105)+(AR105+AS105+AQ105+(AT$88*AT105+AU$88*AU105+AV$88*AV105+AW$88*AW105+AX$88*AX105+AY$88*AY105+AZ$88*AZ105+BA$88*BA105+BB$88*BB105))*#REF! -> #REF! | BE105: =BC105*BD105 -> #REF! | BF105: =BC105+BE105 -> #REF!
BC106: =SUM(AL106:AO106)+(AR106+AS106+AQ106+(AT$88*AT106+AU$88*AU106+AV$88*AV106+AW$88*AW106+AX$88*AX106+AY$88*AY106+AZ$88*AZ106+BA$88*BA106+BB$88*BB106))*#REF! -> #REF! | BE106: =BC106*BD106 -> #REF! | BF106: =BC106+BE106 -> #REF!
BC107: =SUM(AL107:AO107)+(AR107+AS107+AQ107+(AT$88*AT107+AU$88*AU107+AV$88*AV107+AW$88*AW107+AX$88*AX107+AY$88*AY107+AZ$88*AZ107+BA$88*BA107+BB$88*BB107))*#REF! -> #REF! | BE107: =BC107*BD107 -> #REF! | BF107: =BC107+BE107 -> #REF!

Sheet Sheet2
A3: =30 / 2 * (543.7 + 297.7) / (1 - 0 -0) / 3600 -> 3.5058333

Sheet Resin Recycle (2)
B2: 2. Re-cycle Cost Caliclation
G3: =Anneal!E2 -> 2.2 | H3: JPY/PHP
F4: Electricity Cost | G4: 7 | H4: PHP/kWh | M4: Rate | N4: 319.4 | O4: JPY/hr
C6: Resin | D6: Recycle Machine | E6: Machine Capacity | F6: Electric power Consumption | J6: Total Qty of machine | M6: Man Charge | Q6: FEAP Recycle cost
E7: kg/h-machine | F7: kWh | H7: JPY/hr-machine | J7: machines | K7: JPY/hr | L7: kg/hr | M7: MP | N7: JPY/hr | O7: JPY/hr | Q7: JPY/kg
C8: PBT | E8: 1.8 | F8: 0.75 | H8: =G4*G3*F8 -> 11.55 | J8: 7 | K8: =J8*H8 -> 80.85 | L8: =E8*J8 -> 12.6 | M8: 2 | N8: =M8*N4 -> 638.8 | O8: =K8+N8 -> 719.65 | Q8: =O8/L8 -> 57.115079
Q10: Disposal cost
Q11: PHP/kg
Q12: 8

Sheet Anneal
C1: normal anneal cost
B2: 1 | C2: forex | D2: php | E2: 2.2 | F2: jpy/php
C3: heater capacity | D3: kW | E3: 13.5 | F3: kWh | G3: =E3*0.7 -> 9.45 | H3: *100％は立ち上げのみとみなし、70%の消費電力量とする。
C4: electricity | D4: kW | E4: 7 | F4: php
E5: =E2*G3*E4 -> 145.53 | F5: JPY/hour
B6: 2 | C6: manhour | D6: operator | E6: =MTMH!H5 -> 319.39939 | F6: JPY/hour*man
C7: operator shifting | E7: 5 | F7: man power / shift
E8: 8 | F8: annealing machine
E9: =E6*E7/E8 -> 199.62462 | F9: JPY/hour*machine
C11: electricity on heater | D11: actual time ( including heat up and cool down ) | E11: electricity | F11: manpower | G11: total
C12: [hour]
B13: POM | C13: 4 | D13: 5 | E13: =C13*E5 -> 582.12 | F13: =D13*E9 -> 998.12311 | G13: =E13+F13 -> 1580.2431
B14: PBT | C14: 2 | D14: 3 | E14: =C14*E5 -> 291.06 | F14: =E9*D14 -> 598.87386 | G14: =E14+F14 -> 889.93386
L15: =G13/D16/D17 -> 2469.1299 | M15: =G14/D16/D18 -> 1668.626
B16: 占有率 | C16: occupied | D16: 0.8 | L16: =L15 -> 2469.1299 | M16: =M15 -> 1668.626
B17: OA | C17: POM | D17: =C13/D13 -> 0.8 | L17: =L16 -> 2469.1299 | M17: =M16 -> 1668.626
C18: PBT | D18: =C14/D14 -> 0.66666667 | L18: =L17 -> 2469.1299 | M18: =M17 -> 1668.626
F19: machine in side area | H19: layer | L19: POM | M19: PBT
B20: Size | C20: A | D20: 10 | E20: pcs / tray | F20: 6 | G20: tray /machine | H20: 16 | I20: layer | J20: =D20*F20*H20 -> 960 | L20: =L15/J20 -> 2.5720103 | M20: =M15/J20 -> 1.7381521
C21: B | D21: 12 | E21: pcs / tray | F21: 6 | G21: tray /machine | H21: 16 | I21: layer | J21: =D21*F21*H21 -> 1152 | L21: =L16/J21 -> 2.1433419 | M21: =M16/J21 -> 1.4484601
C22: C | D22: 15 | E22: pcs / tray | F22: 6 | G22: tray /machine | H22: 16 | I22: layer | J22: =D22*F22*H22 -> 1440 | L22: =L17/J22 -> 1.7146735 | M22: =M17/J22 -> 1.1587681
C23: D | D23: 60 | E23: pcs / tray | F23: 6 | G23: tray /machine | H23: 16 | I23: layer | J23: =D23*F23*H23 -> 5760 | L23: =L18/J23 -> 0.42866838 | M23: =M18/J23 -> 0.28969201
C26: water absorption
B27: 1 | C27: forex | D27: php | E27: 2.2 | F27: jpy/php
C28: heater capacity | D28: kW | E28: 13.5 | F28: kWh | G28: =E28*0.7 -> 9.45 | H28: *100％は立ち上げのみとみなし、70%の消費電力量とする。
C29: electricity | D29: kW | E29: 7 | F29: php
E30: =E27*G28*E29 -> 145.53 | F30: JPY/hour
B31: 2 | C31: manhour | D31: operator | E31: =E6 -> 319.39939 | F31: JPY/hour
C32: operator shifting | E32: 5 | F32: man power / shift
E33: 8 | F33: annealing machine
E34: =E31*E32/E33 -> 199.62462 | F34: JPY/hour
C36: electricity on heater | D36: actual time ( including heat up and cool down ) | E36: electricity | F36: manpower | G36: total
C37: [hour]
B38: I | C38: 4 | D38: 5 | E38: =C38*E30 -> 582.12 | F38: =D38*E34 -> 998.12311 | G38: =E38+F38 -> 1580.2431
B39: II | C39: 6 | D39: 7 | E39: =C39*E30 -> 873.18 | F39: =E34*D39 -> 1397.3723 | G39: =E39+F39 -> 2270.5523
B40: III | C40: 8 | D40: 9 | E40: =C40*E30 -> 1164.24 | F40: =E34*D40 -> 1796.6216 | G40: =E40+F40 -> 2960.8616 | L40: =G38/D41/D42 -> 2469.1299 | M40: =G39/D41/D43 -> 3311.2222 | N40: =G40/D41/D44 -> 4163.7116
B41: 占有率 | C41: occupied | D41: 0.8 | L41: =L40 -> 2469.1299 | M41: =M40 -> 3311.2222 | N41: =N40 -> 4163.7116
B42: OA | C42: I | D42: =C38/D38 -> 0.8 | L42: =L41 -> 2469.1299 | M42: =M41 -> 3311.2222 | N42: =N41 -> 4163.7116
C43: II | D43: =C39/D39 -> 0.85714286 | L43: =L42 -> 2469.1299 | M43: =M42 -> 3311.2222 | N43: =N42 -> 4163.7116
C44: III | D44: =C40/D40 -> 0.88888889 | F44: machine in side area | H44: layer | L44: 4h | M44: 5h | N44: 9h
B45: Size | C45: A | D45: 10 | E45: pcs / tray | F45: 3 | G45: tray /machine | H45: 14 | I45: layer | J45: =D45*F45*H45 -> 420 | L45: =L40/J45 -> 5.8788806 | M45: =M40/J45 -> 7.8838623 | N45: =N40/J45 -> 9.9135991
C46: B | D46: 12 | E46: pcs / tray | F46: 3 | G46: tray /machine | H46: 14 | I46: layer | J46: =D46*F46*H46 -> 504 | L46: =L41/J46/2 -> 2.4495336 | M46: =M41/J46/2 -> 3.2849426 | N46: =N41/J46/2 -> 4.1306663 | O46: 2layer application
C47: C | D47: 15 | E47: pcs / tray | F47: 3 | G47: tray /machine | H47: 14 | I47: layer | J47: =D47*F47*H47 -> 630 | L47: =L42/J47 -> 3.9192537 | M47: =M42/J47 -> 5.2559082 | N47: =N42/J47 -> 6.6090661
C48: D | D48: 60 | E48: pcs / tray | F48: 3 | G48: tray /machine | H48: 14 | I48: layer | J48: =D48*F48*H48 -> 2520 | L48: =L43/J48 -> 0.97981343 | M48: =M43/J48 -> 1.3139771 | N48: =N43/J48 -> 1.6522665

Sheet Resin Recycle
B2: 1. Resin Purchasing Price
C4: Resin Name | D4: Color | E4: P/N# | F4: Purchasing Price (original forex) | I4: Purchasing Price (JPY)
C5: BASF ULTRADUR B4520 Q120 | D5: Black | F5: 2.9 | G5: USD | H5: /kg | I5: =IF(G5="USD",F5*$F$28,IF(G5="PHP",F5*$F$29,F5)) -> 304.5 | J5: JPY | K5: /kg
C6: PBT DURANEX 2002 ED | D6: Black | F6: 397.1 | G6: JPY | H6: /kg | I6: =IF(G6="USD",F6*$F$28,IF(G6="PHP",F6*$F$29,F6)) -> 397.1 | J6: JPY | K6: /kg
C7: IUPITAL F30-03 E9000 BLACK | D7: Black | F7: 1.98 | G7: USD | H7: /kg | I7: =IF(G7="USD",F7*$F$28,IF(G7="PHP",F7*$F$29,F7)) -> 207.9 | J7: JPY | K7: /kg
C8: IUPITAL F30-73R1 BLACK | D8: Black | F8: 345.5 | G8: JPY | H8: /kg | I8: =IF(G8="USD",F8*$F$28,IF(G8="PHP",F8*$F$29,F8)) -> 345.5 | J8: JPY | K8: /kg
C9: IUPITAL F30-03 E9003 NATURAL | D9: Natural | F9: 2.03 | G9: USD | H9: /kg | I9: =IF(G9="USD",F9*$F$28,IF(G9="PHP",F9*$F$29,F9)) -> 213.15 | J9: JPY | K9: /kg
C10: IUPITAL FX-11J BLACK | D10: Black | F10: 3.98 | G10: USD | H10: /kg | I10: =IF(G10="USD",F10*$F$28,IF(G10="PHP",F10*$F$29,F10)) -> 417.9 | J10: JPY | K10: /kg
C11: DURACON NW-02 BLACK | D11: Black | F11: 4.7 | G11: USD | H11: /kg | I11: =IF(G11="USD",F11*$F$28,IF(G11="PHP",F11*$F$29,F11)) -> 493.5 | J11: JPY | K11: /kg
C12: IUPITAL F20-73R1 BLUE | D12: Blue | F12: 1623.68 | G12: JPY | H12: /kg | I12: =IF(G12="USD",F12*$F$28,IF(G12="PHP",F12*$F$29,F12)) -> 1623.68 | J12: JPY | K12: /kg
C13: IUPITAL F30-73R1 NATURAL | D13: Natural | F13: 345.5 | G13: JPY | H13: /kg | I13: =IF(G13="USD",F13*$F$28,IF(G13="PHP",F13*$F$29,F13)) -> 345.5 | J13: JPY | K13: /kg
C14: POM IUPITAL F30-03, FOP 3CA030 ORG | D14: Orange | F14: 3.15 | G14: USD | H14: /kg | I14: =IF(G14="USD",F14*$F$28,IF(G14="PHP",F14*$F$29,F14)) -> 330.75 | J14: JPY | K14: /kg
C15: POLYBUTYL TERAPTHALATE BASF | F15: 2.9 | G15: USD | H15: /kg | I15: =IF(G15="USD",F15*$F$28,IF(G15="PHP",F15*$F$29,F15)) -> 304.5 | J15: JPY | K15: /kg
C16: ULTRADUR B4520 | D16: Green | F16: 6.652 | G16: USD | H16: /kg | I16: =IF(G16="USD",F16*$F$28,IF(G16="PHP",F16*$F$29,F16)) -> 698.46 | J16: JPY | K16: /kg
C17: PBT PB-25K | D17: Black | F17: 1494.07 | G17: JPY | H17: /kg | I17: =IF(G17="USD",F17*$F$28,IF(G17="PHP",F17*$F$29,F17)) -> 1494.07 | J17: JPY | K17: /kg
C18: PBT 1401-X34 | F18: 343.23 | G18: JPY | H18: /kg | I18: =IF(G18="USD",F18*$F$28,IF(G18="PHP",F18*$F$29,F18)) -> 343.23 | J18: JPY | K18: /kg
C19: POM IUPITAL F30-03, FOP 2CA087 YEL | D19: Yellow | F19: 3.7 | G19: USD | H19: /kg | I19: =IF(G19="USD",F19*$F$28,IF(G19="PHP",F19*$F$29,F19)) -> 388.5 | J19: JPY | K19: /kg
C20: POM IUPITAL F30-03, FOP 7CA311 BLU | D20: Blue | F20: 3.7 | G20: USD | H20: /kg | I20: =IF(G20="USD",F20*$F$28,IF(G20="PHP",F20*$F$29,F20)) -> 388.5 | J20: JPY | K20: /kg
C21: POM IUPITAL F30-03, FOP 5CA120 GRN | D21: Green | F21: 3.87 | G21: USD | H21: /kg | I21: =IF(G21="USD",F21*$F$28,IF(G21="PHP",F21*$F$29,F21)) -> 406.35 | J21: JPY | K21: /kg
C22: POM IUPITAL F30-03, FOP 3CA030 ORG | D22: Orange | F22: 3.87 | G22: USD | H22: /kg | I22: =IF(G22="USD",F22*$F$28,IF(G22="PHP",F22*$F$29,F22)) -> 406.35 | J22: JPY | K22: /kg
C23: PPS DIC FZ-1140K | F23: 736.5 | G23: JPY | H23: /kg | I23: =IF(G23="USD",F23*$F$28,IF(G23="PHP",F23*$F$29,F23)) -> 736.5 | J23: JPY | K23: /kg
C24: PPS DIC FZ-1040K | F24: 776.9 | G24: JPY | H24: /kg | I24: =IF(G24="USD",F24*$F$28,IF(G24="PHP",F24*$F$29,F24)) -> 776.9 | J24: JPY | K24: /kg
C25: PP J715M | D25: Natural | F25: 2.325 | G25: USD | H25: /kg | I25: =IF(G25="USD",F25*$F$28,IF(G25="PHP",F25*$F$29,F25)) -> 244.125 | J25: JPY | K25: /kg
C26: PP master batch | D26: Blue | F26: 366 | G26: PHP | H26: /kg | I26: =IF(G26="USD",F26*$F$28,IF(G26="PHP",F26*$F$29,F26)) -> 805.2 | J26: JPY | K26: /kg
C28: FOREX ; | F28: 105 | G28: JPY/USD
F29: 2.2 | G29: JPY/PHP
B31: 2. Re-cycle Cost Caliclation
C33: Resin | D33: Recycle machine | F33: Electric power consumption
F34: 0.75 | G34: kWh
C39: Recycle cost | F39: =O48 -> 57.114983 | G39: JPY/h-kg
C40: Disporsal cost | F40: 17.6 | G40: JPY/kg | H40: Virgin material need to add disporsal cost /バージン材は廃却コストを加算する。
C42: Recycle Material Cost | F42: リサイクルコスト
B43: 為替 | C43: Forex | E43: =Anneal!E2 -> 2.2 | F43: JPY/PHP | G43: Electricity
B44: 電気代 | C44: Electricity | E44: 0.75 | F44: kWh | G44: 7 | H44: PHP/kWh | I44: =E44*G44*E43 -> 11.55 | J44: JPY/h-machine | M44: 7 | N44: machine | O44: =I44*M44 -> 80.85 | P44: JPY/h
B45: 人件費 | C45: Manhour | E45: 1 | F45: operator | G45: =Anneal!E6 -> 319.39939 | H45: JPY/h | I45: =G45 -> 319.39939 | J45: JPY/h-man | M45: 2 | N45: operator | O45: =M45*I45 -> 638.79879 | P45: JPY/h
N46: Total | O46: =O44+O45 -> 719.64879 | P46: JPY/h
B47: 処理能力 | C47: Machine Capability | E47: 1.8 | F47: kg/h | G47: /machine | O47: =E47*M44 -> 12.6 | P47: kg/h
O48: =O46/O47 -> 57.114983 | P48: JPY/h-kg
E50: Disporsal cost | F50: 8 | G50: PHP/kg

Sheet MTMH
F3: =1/F4 -> 2.1299255 | H3: hourly | I3: 2018 | J3: 2019 | K3: 20 | L3: 21 | M3: 22 | N3: 23 | O3: 24 | P3: 25 | Q3: 26 | R3: 27 | S3: 28 | T3: 29 | U3: 30 | V3: 31
C4: FEAP | D4: OPERATOR | E4: 1004.1803 | F4: 0.4695 | G4: =E4/F4 -> 2138.8291 | H4: =G4/8 -> 267.35364 | I4: =H4*1.25 -> 334.19205 | J4: =I4*1.05 -> 350.90165 | K4: =J4*1.05 -> 368.44673 | L4: =K4*1.05 -> 386.86907 | M4: =L4*1.05 -> 406.21252 | N4: =M4*1.05 -> 426.52315 | O4: =N4*1.05 -> 447.8493 | P4: =O4*1.05 -> 470.24177 | Q4: =P4*1.05 -> 493.75386 | ... V4: =U4*1.05 -> 630.16894
D5: SUB LEADER | E5: 1199.6641 | F5: 0.4695 | G5: =E5/F5 -> 2555.1952 | H5: =G5/8 -> 319.39939 | J5: =AVERAGE(M4:Q4) -> 448.91612
D6: TEAM LEADER | E6: 1291.7479 | F6: 0.4695 | G6: =E6/F6 -> 2751.3268 | H6: =G6/8 -> 343.91585
D7: CONTROLLER | E7: 1125.6196 | F7: 0.4695 | G7: =E7/F7 -> 2397.4858 | H7: =G7/8 -> 299.68572
D8: INSPECTOR | E8: 939.91451 | F8: 0.4695 | G8: =E8/F8 -> 2001.9478 | H8: =G8/8 -> 250.24348
C9: agency | D9: ALL POSITION | E9: 544.75968 | F9: 0.4695 | G9: =E9/F9 -> 1160.2975 | H9: =G9/8 -> 145.03719
C14: 2017 | D14: 2018 | E14: 2019 | F14: 20 | G14: 21 | H14: 22 | I14: 23 | J14: 24 | K14: 25 | L14: 26 | M14: 27 | N14: 28
A15: hori | B15: MH | C15: 176.163 | D15: =C15*1.25 -> 220.20375 | E15: 297.65682 | F15: =E15*1.05 -> 312.53966 | G15: =F15*1.05 -> 328.16665 | H15: =G15*1.05 -> 344.57498 | I15: =H15*1.05 -> 361.80373 | J15: =I15*1.05 -> 379.89392 | K15: =J15*1.05 -> 398.88861 | L15: =K15*1.05 -> 418.83304 | M15: =L15*1.05 -> 439.77469 | N15: =M15*1.05 -> 461.76343
A16: hori | B16: MT | C16: 565.3723 | D16: =C16*1.02 -> 576.67975 | E16: 543.66751 | F16: =E16*1.02 -> 554.54086 | G16: =F16*1.02 -> 565.63168 | H16: =G16*1.02 -> 576.94431 | I16: =H16*1.02 -> 588.4832 | J16: =I16*1.02 -> 600.25286 | K16: =J16*1.02 -> 612.25792 | L16: =K16*1.02 -> 624.50308 | M16: =L16*1.02 -> 636.99314 | N16: =M16*1.02 -> 649.733
A17: vertical | B17: MT | C17: 655.44094 | D17: =C17*1.02 -> 668.54976 | E17: =D17*1.02 -> 681.92075 | F17: =E17*1.02 -> 695.55917 | G17: =F17*1.02 -> 709.47035 | H17: =G17*1.02 -> 723.65976 | I17: =H17*1.02 -> 738.13296 | J17: =I17*1.02 -> 752.89561 | K17: =J17*1.02 -> 767.95353 | ... N17: =M17*1.02 -> 814.95843
E18: =AVERAGE(H15:K15) -> 371.29031
E19: =AVERAGE(H16:K16) -> 594.48457
E20: =AVERAGE(H17:K17) -> 745.66046
E22: 2019年用の値
E23: Verticalは未計算
E26: 1162.1903
